{
"meta":{"test_sets":[],"test_metrics":[],"learn_metrics":[{"best_value":"Min","name":"Logloss"}],"launch_mode":"Train","parameters":"","iteration_count":1000,"learn_sets":["learn"],"name":"experiment"},
"iterations":[
{"learn":[0.6899144068],"iteration":0,"passed_time":0.05513286378,"remaining_time":55.07773091},
{"learn":[0.6870031299],"iteration":1,"passed_time":0.05725492895,"remaining_time":28.57020955},
{"learn":[0.6837433508],"iteration":2,"passed_time":0.0602745328,"remaining_time":20.0312364},
{"learn":[0.6808964035],"iteration":3,"passed_time":0.0623315268,"remaining_time":15.52055017},
{"learn":[0.6779019447],"iteration":4,"passed_time":0.06424249886,"remaining_time":12.78425727},
{"learn":[0.6752501199],"iteration":5,"passed_time":0.06588950194,"remaining_time":10.91569415},
{"learn":[0.6726925006],"iteration":6,"passed_time":0.06767724278,"remaining_time":9.600500297},
{"learn":[0.6701797109],"iteration":7,"passed_time":0.0701766256,"remaining_time":8.701901574},
{"learn":[0.6673085522],"iteration":8,"passed_time":0.07369375951,"remaining_time":8.114501742},
{"learn":[0.6645867531],"iteration":9,"passed_time":0.07595260747,"remaining_time":7.51930814},
{"learn":[0.6613772205],"iteration":10,"passed_time":0.07784146373,"remaining_time":6.998655239},
{"learn":[0.6586996617],"iteration":11,"passed_time":0.08066308974,"remaining_time":6.641261055},
{"learn":[0.656333757],"iteration":12,"passed_time":0.08309029168,"remaining_time":6.308470607},
{"learn":[0.6536767037],"iteration":13,"passed_time":0.08487030205,"remaining_time":5.97729413},
{"learn":[0.6510230079],"iteration":14,"passed_time":0.08656313279,"remaining_time":5.684312387},
{"learn":[0.648493492],"iteration":15,"passed_time":0.08934198114,"remaining_time":5.49453184},
{"learn":[0.6458925018],"iteration":16,"passed_time":0.09245295406,"remaining_time":5.345956108},
{"learn":[0.6434283407],"iteration":17,"passed_time":0.0947263783,"remaining_time":5.167850194},
{"learn":[0.6410103984],"iteration":18,"passed_time":0.09666045999,"remaining_time":4.990732171},
{"learn":[0.6388953811],"iteration":19,"passed_time":0.09861113912,"remaining_time":4.831945817},
{"learn":[0.6365698421],"iteration":20,"passed_time":0.1008395495,"remaining_time":4.701043758},
{"learn":[0.6347126049],"iteration":21,"passed_time":0.103071785,"remaining_time":4.582009352},
{"learn":[0.6324778759],"iteration":22,"passed_time":0.1050810761,"remaining_time":4.463661363},
{"learn":[0.6301563853],"iteration":23,"passed_time":0.107334962,"remaining_time":4.364955123},
{"learn":[0.6281282814],"iteration":24,"passed_time":0.109583655,"remaining_time":4.273762545},
{"learn":[0.6263371057],"iteration":25,"passed_time":0.1109552049,"remaining_time":4.156552676},
{"learn":[0.6246524379],"iteration":26,"passed_time":0.1119254108,"remaining_time":4.033460173},
{"learn":[0.6225916063],"iteration":27,"passed_time":0.1136564802,"remaining_time":3.945503528},
{"learn":[0.6210256091],"iteration":28,"passed_time":0.1151918342,"remaining_time":3.856940381},
{"learn":[0.6187663961],"iteration":29,"passed_time":0.117458064,"remaining_time":3.797810737},
{"learn":[0.6172859055],"iteration":30,"passed_time":0.1188205234,"remaining_time":3.714099585},
{"learn":[0.6149591656],"iteration":31,"passed_time":0.1204560352,"remaining_time":3.643795064},
{"learn":[0.6129021293],"iteration":32,"passed_time":0.1221571898,"remaining_time":3.579575834},
{"learn":[0.6114907167],"iteration":33,"passed_time":0.1230124389,"remaining_time":3.49500047},
{"learn":[0.6096288806],"iteration":34,"passed_time":0.1248164962,"remaining_time":3.44136911},
{"learn":[0.6082703759],"iteration":35,"passed_time":0.1254931245,"remaining_time":3.360427002},
{"learn":[0.6068076955],"iteration":36,"passed_time":0.1267582028,"remaining_time":3.299139169},
{"learn":[0.6046931623],"iteration":37,"passed_time":0.1294178228,"remaining_time":3.276314356},
{"learn":[0.6030224326],"iteration":38,"passed_time":0.1312990683,"remaining_time":3.235343709},
{"learn":[0.600777156],"iteration":39,"passed_time":0.134520194,"remaining_time":3.228484656},
{"learn":[0.5992569856],"iteration":40,"passed_time":0.1364685033,"remaining_time":3.192031578},
{"learn":[0.5980284526],"iteration":41,"passed_time":0.1374765848,"remaining_time":3.135775435},
{"learn":[0.5964767442],"iteration":42,"passed_time":0.1388012379,"remaining_time":3.089134528},
{"learn":[0.5946838109],"iteration":43,"passed_time":0.1414157682,"remaining_time":3.072578963},
{"learn":[0.5929383313],"iteration":44,"passed_time":0.1442537833,"remaining_time":3.061385846},
{"learn":[0.5912513893],"iteration":45,"passed_time":0.1463166499,"remaining_time":3.034480087},
{"learn":[0.5897827595],"iteration":46,"passed_time":0.1486731714,"remaining_time":3.014585795},
{"learn":[0.5882513067],"iteration":47,"passed_time":0.1521055132,"remaining_time":3.016759344},
{"learn":[0.5870665206],"iteration":48,"passed_time":0.1543949447,"remaining_time":2.996522294},
{"learn":[0.5859685063],"iteration":49,"passed_time":0.1554408277,"remaining_time":2.953375727},
{"learn":[0.5846007832],"iteration":50,"passed_time":0.157034368,"remaining_time":2.922070887},
{"learn":[0.5835368756],"iteration":51,"passed_time":0.1584340843,"remaining_time":2.888375229},
{"learn":[0.582099968],"iteration":52,"passed_time":0.1601293945,"remaining_time":2.861179937},
{"learn":[0.580570037],"iteration":53,"passed_time":0.1649736523,"remaining_time":2.890093982},
{"learn":[0.5790549114],"iteration":54,"passed_time":0.1678828095,"remaining_time":2.884531908},
{"learn":[0.5775802854],"iteration":55,"passed_time":0.1698105411,"remaining_time":2.86252055},
{"learn":[0.5762767052],"iteration":56,"passed_time":0.1710798126,"remaining_time":2.830320408},
{"learn":[0.5748790947],"iteration":57,"passed_time":0.1727454443,"remaining_time":2.805624285},
{"learn":[0.5734090523],"iteration":58,"passed_time":0.1746331208,"remaining_time":2.785250282},
{"learn":[0.5719759491],"iteration":59,"passed_time":0.1762577606,"remaining_time":2.761371583},
{"learn":[0.5710280556],"iteration":60,"passed_time":0.1795031153,"remaining_time":2.763170907},
{"learn":[0.5696480939],"iteration":61,"passed_time":0.1837209699,"remaining_time":2.779520479},
{"learn":[0.5687878866],"iteration":62,"passed_time":0.1847253356,"remaining_time":2.747422849},
{"learn":[0.5674341892],"iteration":63,"passed_time":0.1866133549,"remaining_time":2.729220315},
{"learn":[0.5663938826],"iteration":64,"passed_time":0.1884124251,"remaining_time":2.710240269},
{"learn":[0.5652026374],"iteration":65,"passed_time":0.1905634187,"remaining_time":2.696761107},
{"learn":[0.5639381679],"iteration":66,"passed_time":0.1933982138,"remaining_time":2.693142291},
{"learn":[0.5629234706],"iteration":67,"passed_time":0.1978938333,"remaining_time":2.712309598},
{"learn":[0.5616958004],"iteration":68,"passed_time":0.1997432096,"remaining_time":2.695085916},
{"learn":[0.5607185824],"iteration":69,"passed_time":0.2013329885,"remaining_time":2.674852562},
{"learn":[0.559388306],"iteration":70,"passed_time":0.2035938,"remaining_time":2.66392451},
{"learn":[0.5574930416],"iteration":71,"passed_time":0.2061142633,"remaining_time":2.656583838},
{"learn":[0.5563323603],"iteration":72,"passed_time":0.2080883642,"remaining_time":2.642437173},
{"learn":[0.5553499305],"iteration":73,"passed_time":0.2099023688,"remaining_time":2.626616129},
{"learn":[0.55426478],"iteration":74,"passed_time":0.211788933,"remaining_time":2.612063507},
{"learn":[0.5528961594],"iteration":75,"passed_time":0.2138084238,"remaining_time":2.59946031},
{"learn":[0.5517730125],"iteration":76,"passed_time":0.2167165895,"remaining_time":2.597784573},
{"learn":[0.5504628705],"iteration":77,"passed_time":0.2185517093,"remaining_time":2.583393282},
{"learn":[0.5487938595],"iteration":78,"passed_time":0.2201500116,"remaining_time":2.566558996},
{"learn":[0.5474034125],"iteration":79,"passed_time":0.2218826726,"remaining_time":2.551650735},
{"learn":[0.546336622],"iteration":80,"passed_time":0.2274384903,"remaining_time":2.580444106},
{"learn":[0.5448624153],"iteration":81,"passed_time":0.2291537563,"remaining_time":2.565404248},
{"learn":[0.5437289414],"iteration":82,"passed_time":0.2308646002,"remaining_time":2.550636607},
{"learn":[0.542995927],"iteration":83,"passed_time":0.2322683271,"remaining_time":2.532830805},
{"learn":[0.5424068017],"iteration":84,"passed_time":0.2333566185,"remaining_time":2.512015364},
{"learn":[0.5415469427],"iteration":85,"passed_time":0.234881942,"remaining_time":2.49630343},
{"learn":[0.540379053],"iteration":86,"passed_time":0.2372412493,"remaining_time":2.489669663},
{"learn":[0.5393171451],"iteration":87,"passed_time":0.2418803068,"remaining_time":2.506759543},
{"learn":[0.5385410765],"iteration":88,"passed_time":0.2438646907,"remaining_time":2.496188014},
{"learn":[0.537960947],"iteration":89,"passed_time":0.244837452,"remaining_time":2.475578682},
{"learn":[0.5367760679],"iteration":90,"passed_time":0.2467747123,"remaining_time":2.465035313},
{"learn":[0.5359654759],"iteration":91,"passed_time":0.2483810468,"remaining_time":2.45141294},
{"learn":[0.5349165143],"iteration":92,"passed_time":0.2510482791,"remaining_time":2.448395582},
{"learn":[0.5343678649],"iteration":93,"passed_time":0.2520155288,"remaining_time":2.429000735},
{"learn":[0.5331567356],"iteration":94,"passed_time":0.253909435,"remaining_time":2.41882146},
{"learn":[0.5320182501],"iteration":95,"passed_time":0.2564781932,"remaining_time":2.415169653},
{"learn":[0.5310351799],"iteration":96,"passed_time":0.2583380258,"remaining_time":2.404940591},
{"learn":[0.5300801154],"iteration":97,"passed_time":0.2611429955,"remaining_time":2.403581449},
{"learn":[0.529056804],"iteration":98,"passed_time":0.2631732683,"remaining_time":2.395142573},
{"learn":[0.5278625224],"iteration":99,"passed_time":0.2649720729,"remaining_time":2.384748656},
{"learn":[0.5270016974],"iteration":100,"passed_time":0.266727542,"remaining_time":2.374139211},
{"learn":[0.5262016245],"iteration":101,"passed_time":0.2684300444,"remaining_time":2.363237058},
{"learn":[0.5251310124],"iteration":102,"passed_time":0.2725250372,"remaining_time":2.37334911},
{"learn":[0.524477893],"iteration":103,"passed_time":0.2749512344,"remaining_time":2.368810635},
{"learn":[0.5234094356],"iteration":104,"passed_time":0.2768776474,"remaining_time":2.360052328},
{"learn":[0.5225534085],"iteration":105,"passed_time":0.2784982646,"remaining_time":2.348843855},
{"learn":[0.5215110636],"iteration":106,"passed_time":0.2801649681,"remaining_time":2.33819922},
{"learn":[0.5206801475],"iteration":107,"passed_time":0.2821337142,"remaining_time":2.330215492},
{"learn":[0.5194724379],"iteration":108,"passed_time":0.2863099538,"remaining_time":2.34038687},
{"learn":[0.5187221015],"iteration":109,"passed_time":0.2887129893,"remaining_time":2.33595055},
{"learn":[0.5180214091],"iteration":110,"passed_time":0.2905404072,"remaining_time":2.326940739},
{"learn":[0.5172879031],"iteration":111,"passed_time":0.2921781214,"remaining_time":2.316555106},
{"learn":[0.5163363391],"iteration":112,"passed_time":0.2939202147,"remaining_time":2.307143632},
{"learn":[0.5154754791],"iteration":113,"passed_time":0.2955149814,"remaining_time":2.296721698},
{"learn":[0.5148280848],"iteration":114,"passed_time":0.2975746921,"remaining_time":2.290031326},
{"learn":[0.5139831261],"iteration":115,"passed_time":0.2992850476,"remaining_time":2.280758466},
{"learn":[0.5133561323],"iteration":116,"passed_time":0.301384834,"remaining_time":2.274553918},
{"learn":[0.5125802222],"iteration":117,"passed_time":0.303236869,"remaining_time":2.266567106},
{"learn":[0.5119682637],"iteration":118,"passed_time":0.3049264359,"remaining_time":2.257480588},
{"learn":[0.5110745528],"iteration":119,"passed_time":0.3068304183,"remaining_time":2.250089734},
{"learn":[0.5100414057],"iteration":120,"passed_time":0.3083955109,"remaining_time":2.24032772},
{"learn":[0.5093534815],"iteration":121,"passed_time":0.3100032373,"remaining_time":2.231006905},
{"learn":[0.5081884466],"iteration":122,"passed_time":0.3122683624,"remaining_time":2.226498812},
{"learn":[0.5075442059],"iteration":123,"passed_time":0.3151476866,"remaining_time":2.226365915},
{"learn":[0.5069965114],"iteration":124,"passed_time":0.3172987486,"remaining_time":2.221091241},
{"learn":[0.5063835113],"iteration":125,"passed_time":0.3189553127,"remaining_time":2.212436058},
{"learn":[0.5060234831],"iteration":126,"passed_time":0.3204541812,"remaining_time":2.202807088},
{"learn":[0.5054022351],"iteration":127,"passed_time":0.3220035669,"remaining_time":2.1936493},
{"learn":[0.5047265268],"iteration":128,"passed_time":0.323423236,"remaining_time":2.183733632},
{"learn":[0.5042555857],"iteration":129,"passed_time":0.325038053,"remaining_time":2.175254663},
{"learn":[0.5035827965],"iteration":130,"passed_time":0.3280070649,"remaining_time":2.175863659},
{"learn":[0.5031713832],"iteration":131,"passed_time":0.3304326678,"remaining_time":2.172845119},
{"learn":[0.5021794639],"iteration":132,"passed_time":0.332936221,"remaining_time":2.170343636},
{"learn":[0.5013061055],"iteration":133,"passed_time":0.3353025015,"remaining_time":2.166954972},
{"learn":[0.5007553005],"iteration":134,"passed_time":0.3370217987,"remaining_time":2.159435969},
{"learn":[0.499919361],"iteration":135,"passed_time":0.3388339266,"remaining_time":2.152592004},
{"learn":[0.4991873517],"iteration":136,"passed_time":0.3408663653,"remaining_time":2.147209294},
{"learn":[0.498504169],"iteration":137,"passed_time":0.3435904531,"remaining_time":2.146195439},
{"learn":[0.497789537],"iteration":138,"passed_time":0.3458657211,"remaining_time":2.142376877},
{"learn":[0.4971714428],"iteration":139,"passed_time":0.348555799,"remaining_time":2.14112848},
{"learn":[0.4967768081],"iteration":140,"passed_time":0.3514225066,"remaining_time":2.140935696},
{"learn":[0.4961721391],"iteration":141,"passed_time":0.3535243245,"remaining_time":2.136083594},
{"learn":[0.4955559289],"iteration":142,"passed_time":0.3558065986,"remaining_time":2.132351434},
{"learn":[0.4951578575],"iteration":143,"passed_time":0.3578981079,"remaining_time":2.127505419},
{"learn":[0.4945101986],"iteration":144,"passed_time":0.3600989444,"remaining_time":2.123342051},
{"learn":[0.4942172304],"iteration":145,"passed_time":0.3613225482,"remaining_time":2.113489426},
{"learn":[0.4934778057],"iteration":146,"passed_time":0.3644894941,"remaining_time":2.115030874},
{"learn":[0.4928860118],"iteration":147,"passed_time":0.3664345872,"remaining_time":2.109474786},
{"learn":[0.4922027263],"iteration":148,"passed_time":0.3683259051,"remaining_time":2.103660035},
{"learn":[0.4913618816],"iteration":149,"passed_time":0.3703995533,"remaining_time":2.098930802},
{"learn":[0.4908676674],"iteration":150,"passed_time":0.3726484251,"remaining_time":2.09522194},
{"learn":[0.490154195],"iteration":151,"passed_time":0.3755933568,"remaining_time":2.095415569},
{"learn":[0.4895604712],"iteration":152,"passed_time":0.3788149085,"remaining_time":2.097099526},
{"learn":[0.4891766356],"iteration":153,"passed_time":0.3803596052,"remaining_time":2.089507961},
{"learn":[0.4886160161],"iteration":154,"passed_time":0.3854100543,"remaining_time":2.101106425},
{"learn":[0.4879555593],"iteration":155,"passed_time":0.3887158771,"remaining_time":2.103052566},
{"learn":[0.4872287653],"iteration":156,"passed_time":0.3959458512,"remaining_time":2.126002246},
{"learn":[0.4867183526],"iteration":157,"passed_time":0.3979446793,"remaining_time":2.120692531},
{"learn":[0.4860838666],"iteration":158,"passed_time":0.4017185092,"remaining_time":2.124812995},
{"learn":[0.4853822058],"iteration":159,"passed_time":0.4040425113,"remaining_time":2.121223184},
{"learn":[0.4848549587],"iteration":160,"passed_time":0.4070620737,"remaining_time":2.121273788},
{"learn":[0.4843263293],"iteration":161,"passed_time":0.4145110588,"remaining_time":2.144199181},
{"learn":[0.483653524],"iteration":162,"passed_time":0.4164203925,"remaining_time":2.138305942},
{"learn":[0.483274724],"iteration":163,"passed_time":0.4186339526,"remaining_time":2.1340121},
{"learn":[0.4825775832],"iteration":164,"passed_time":0.4269418238,"remaining_time":2.160584381},
{"learn":[0.4823270524],"iteration":165,"passed_time":0.4288783053,"remaining_time":2.154725943},
{"learn":[0.481970257],"iteration":166,"passed_time":0.430804941,"remaining_time":2.148865364},
{"learn":[0.4808953991],"iteration":167,"passed_time":0.4328642048,"remaining_time":2.143708443},
{"learn":[0.4804329042],"iteration":168,"passed_time":0.4353791939,"remaining_time":2.140829054},
{"learn":[0.4799528294],"iteration":169,"passed_time":0.4383303626,"remaining_time":2.140083535},
{"learn":[0.4793287086],"iteration":170,"passed_time":0.4415141134,"remaining_time":2.140439766},
{"learn":[0.4789480777],"iteration":171,"passed_time":0.443574503,"remaining_time":2.135347026},
{"learn":[0.4785931916],"iteration":172,"passed_time":0.445533369,"remaining_time":2.129804024},
{"learn":[0.4780799993],"iteration":173,"passed_time":0.449161415,"remaining_time":2.132226027},
{"learn":[0.4771799072],"iteration":174,"passed_time":0.4511358548,"remaining_time":2.126783315},
{"learn":[0.4766067281],"iteration":175,"passed_time":0.4561829838,"remaining_time":2.135765788},
{"learn":[0.4763652705],"iteration":176,"passed_time":0.4581380298,"remaining_time":2.130212421},
{"learn":[0.475860316],"iteration":177,"passed_time":0.4605408909,"remaining_time":2.126767485},
{"learn":[0.475364349],"iteration":178,"passed_time":0.4633075542,"remaining_time":2.125002805},
{"learn":[0.4746959632],"iteration":179,"passed_time":0.4671882298,"remaining_time":2.128301936},
{"learn":[0.474143617],"iteration":180,"passed_time":0.4719321808,"remaining_time":2.135427934},
{"learn":[0.473661986],"iteration":181,"passed_time":0.4752209628,"remaining_time":2.135883228},
{"learn":[0.4732302364],"iteration":182,"passed_time":0.4775493047,"remaining_time":2.132009737},
{"learn":[0.4727531193],"iteration":183,"passed_time":0.4799399508,"remaining_time":2.128429347},
{"learn":[0.4723113676],"iteration":184,"passed_time":0.4834934985,"remaining_time":2.129984872},
{"learn":[0.4716816888],"iteration":185,"passed_time":0.4879406487,"remaining_time":2.135396172},
{"learn":[0.4710183627],"iteration":186,"passed_time":0.4899178249,"remaining_time":2.129963592},
{"learn":[0.4708428397],"iteration":187,"passed_time":0.4910314784,"remaining_time":2.120838088},
{"learn":[0.470374566],"iteration":188,"passed_time":0.4943516186,"remaining_time":2.121265411},
{"learn":[0.4697124523],"iteration":189,"passed_time":0.4965631073,"remaining_time":2.116926931},
{"learn":[0.4691895336],"iteration":190,"passed_time":0.4995136615,"remaining_time":2.115741111},
{"learn":[0.468865549],"iteration":191,"passed_time":0.5018166275,"remaining_time":2.111811641},
{"learn":[0.4684440087],"iteration":192,"passed_time":0.5038447008,"remaining_time":2.106749604},
{"learn":[0.4680358264],"iteration":193,"passed_time":0.5068680269,"remaining_time":2.105853761},
{"learn":[0.4675050666],"iteration":194,"passed_time":0.5090974416,"remaining_time":2.101658669},
{"learn":[0.4667219069],"iteration":195,"passed_time":0.5110975,"remaining_time":2.096542806},
{"learn":[0.4663619837],"iteration":196,"passed_time":0.5132043979,"remaining_time":2.091894069},
{"learn":[0.4661014274],"iteration":197,"passed_time":0.5156926531,"remaining_time":2.088815696},
{"learn":[0.4660186467],"iteration":198,"passed_time":0.5168794278,"remaining_time":2.080504631},
{"learn":[0.4656676787],"iteration":199,"passed_time":0.522029734,"remaining_time":2.088118936},
{"learn":[0.4651125179],"iteration":200,"passed_time":0.5240975152,"remaining_time":2.083352809},
{"learn":[0.4648858369],"iteration":201,"passed_time":0.5257577845,"remaining_time":2.077003525},
{"learn":[0.4643348373],"iteration":202,"passed_time":0.5276625562,"remaining_time":2.071660381},
{"learn":[0.4639382736],"iteration":203,"passed_time":0.5299638903,"remaining_time":2.067898317},
{"learn":[0.4634663711],"iteration":204,"passed_time":0.532360875,"remaining_time":2.064521442},
{"learn":[0.4630987996],"iteration":205,"passed_time":0.5374520673,"remaining_time":2.071538551},
{"learn":[0.4623700914],"iteration":206,"passed_time":0.5393088443,"remaining_time":2.066047892},
{"learn":[0.4621241583],"iteration":207,"passed_time":0.5405834129,"remaining_time":2.058375303},
{"learn":[0.4615671788],"iteration":208,"passed_time":0.5420484481,"remaining_time":2.051484796},
{"learn":[0.4611879471],"iteration":209,"passed_time":0.5442048717,"remaining_time":2.047246898},
{"learn":[0.4609664795],"iteration":210,"passed_time":0.5469663803,"remaining_time":2.045291346},
{"learn":[0.4607546669],"iteration":211,"passed_time":0.5507687868,"remaining_time":2.047197189},
{"learn":[0.4601399901],"iteration":212,"passed_time":0.5528705093,"remaining_time":2.042765685},
{"learn":[0.459824446],"iteration":213,"passed_time":0.5545684494,"remaining_time":2.036872903},
{"learn":[0.4596142089],"iteration":214,"passed_time":0.5562262398,"remaining_time":2.03087255},
{"learn":[0.4586500413],"iteration":215,"passed_time":0.5582172847,"remaining_time":2.026121996},
{"learn":[0.4579494053],"iteration":216,"passed_time":0.5611995471,"remaining_time":2.024973481},
{"learn":[0.4575946435],"iteration":217,"passed_time":0.5640162659,"remaining_time":2.023214311},
{"learn":[0.4571402138],"iteration":218,"passed_time":0.5681973809,"remaining_time":2.026311208},
{"learn":[0.4566618432],"iteration":219,"passed_time":0.5699799064,"remaining_time":2.02083785},
{"learn":[0.4562385806],"iteration":220,"passed_time":0.5716713256,"remaining_time":2.015076754},
{"learn":[0.4558990958],"iteration":221,"passed_time":0.5736961826,"remaining_time":2.010520856},
{"learn":[0.4553029695],"iteration":222,"passed_time":0.5774953899,"remaining_time":2.012170036},
{"learn":[0.4550310206],"iteration":223,"passed_time":0.5795882219,"remaining_time":2.007859197},
{"learn":[0.4546367323],"iteration":224,"passed_time":0.581617412,"remaining_time":2.003348863},
{"learn":[0.4542125626],"iteration":225,"passed_time":0.583617671,"remaining_time":1.998761404},
{"learn":[0.453740742],"iteration":226,"passed_time":0.5852799626,"remaining_time":1.993045864},
{"learn":[0.4534479511],"iteration":227,"passed_time":0.5870898346,"remaining_time":1.98786558},
{"learn":[0.4532714215],"iteration":228,"passed_time":0.591073138,"remaining_time":1.990032268},
{"learn":[0.453006363],"iteration":229,"passed_time":0.5950599051,"remaining_time":1.992157074},
{"learn":[0.4526461839],"iteration":230,"passed_time":0.5970095648,"remaining_time":1.987447426},
{"learn":[0.4523477829],"iteration":231,"passed_time":0.5987555183,"remaining_time":1.982087233},
{"learn":[0.4518207846],"iteration":232,"passed_time":0.6005907105,"remaining_time":1.977051824},
{"learn":[0.4512871392],"iteration":233,"passed_time":0.602582315,"remaining_time":1.972555783},
{"learn":[0.4508519884],"iteration":234,"passed_time":0.605398851,"remaining_time":1.970766472},
{"learn":[0.4505559665],"iteration":235,"passed_time":0.6082810345,"remaining_time":1.969180976},
{"learn":[0.4505289866],"iteration":236,"passed_time":0.6093623164,"remaining_time":1.961786698},
{"learn":[0.4501223433],"iteration":237,"passed_time":0.6128104812,"remaining_time":1.962023473},
{"learn":[0.4496769861],"iteration":238,"passed_time":0.6148861533,"remaining_time":1.957859258},
{"learn":[0.4493427757],"iteration":239,"passed_time":0.6165535169,"remaining_time":1.95241947},
{"learn":[0.4487705631],"iteration":240,"passed_time":0.6184353797,"remaining_time":1.947686528},
{"learn":[0.4483786287],"iteration":241,"passed_time":0.620696365,"remaining_time":1.944164648},
{"learn":[0.448272574],"iteration":242,"passed_time":0.6224539233,"remaining_time":1.939084856},
{"learn":[0.447878713],"iteration":243,"passed_time":0.6245738364,"remaining_time":1.935155001},
{"learn":[0.4476629124],"iteration":244,"passed_time":0.6263035257,"remaining_time":1.930037396},
{"learn":[0.4471493675],"iteration":245,"passed_time":0.6279891241,"remaining_time":1.924812193},
{"learn":[0.4468393151],"iteration":246,"passed_time":0.6297336639,"remaining_time":1.91979534},
{"learn":[0.4466052143],"iteration":247,"passed_time":0.6325558548,"remaining_time":1.918072592},
{"learn":[0.446292909],"iteration":248,"passed_time":0.6352078517,"remaining_time":1.915827697},
{"learn":[0.446034894],"iteration":249,"passed_time":0.6387083682,"remaining_time":1.916125105},
{"learn":[0.4457430776],"iteration":250,"passed_time":0.6405034523,"remaining_time":1.911303131},
{"learn":[0.4455790673],"iteration":251,"passed_time":0.6443641097,"remaining_time":1.912636326},
{"learn":[0.4454312895],"iteration":252,"passed_time":0.6454903345,"remaining_time":1.905854861},
{"learn":[0.4449779881],"iteration":253,"passed_time":0.6473334661,"remaining_time":1.901223487},
{"learn":[0.4445226209],"iteration":254,"passed_time":0.6531524804,"remaining_time":1.908229796},
{"learn":[0.4442627068],"iteration":255,"passed_time":0.6555147436,"remaining_time":1.905089724},
{"learn":[0.4439817832],"iteration":256,"passed_time":0.6573959585,"remaining_time":1.90056497},
{"learn":[0.4436908125],"iteration":257,"passed_time":0.6595375364,"remaining_time":1.896809504},
{"learn":[0.4431815121],"iteration":258,"passed_time":0.6617060041,"remaining_time":1.893143433},
{"learn":[0.4427550162],"iteration":259,"passed_time":0.6652627689,"remaining_time":1.893440188},
{"learn":[0.442457664],"iteration":260,"passed_time":0.6687312152,"remaining_time":1.893457349},
{"learn":[0.4421354088],"iteration":261,"passed_time":0.6710076091,"remaining_time":1.890090136},
{"learn":[0.4416307915],"iteration":262,"passed_time":0.6727958675,"remaining_time":1.885363324},
{"learn":[0.4414731097],"iteration":263,"passed_time":0.6745397956,"remaining_time":1.880535188},
{"learn":[0.4411972662],"iteration":264,"passed_time":0.6792636126,"remaining_time":1.883995303},
{"learn":[0.4408400309],"iteration":265,"passed_time":0.6831071042,"remaining_time":1.884964716},
{"learn":[0.4403724683],"iteration":266,"passed_time":0.6850182454,"remaining_time":1.880593161},
{"learn":[0.4399318168],"iteration":267,"passed_time":0.687482498,"remaining_time":1.877750704},
{"learn":[0.439624935],"iteration":268,"passed_time":0.6891852005,"remaining_time":1.872841567},
{"learn":[0.43895301],"iteration":269,"passed_time":0.6911514206,"remaining_time":1.868668656},
{"learn":[0.4386399552],"iteration":270,"passed_time":0.6931476664,"remaining_time":1.8645928},
{"learn":[0.4385704528],"iteration":271,"passed_time":0.6945239135,"remaining_time":1.858872827},
{"learn":[0.4382122342],"iteration":272,"passed_time":0.6973111496,"remaining_time":1.856942146},
{"learn":[0.4380113656],"iteration":273,"passed_time":0.6995933305,"remaining_time":1.853667},
{"learn":[0.4377667846],"iteration":274,"passed_time":0.7016867159,"remaining_time":1.849901342},
{"learn":[0.4373774834],"iteration":275,"passed_time":0.7037353669,"remaining_time":1.846030455},
{"learn":[0.4370878347],"iteration":276,"passed_time":0.705755281,"remaining_time":1.842097719},
{"learn":[0.4368386084],"iteration":277,"passed_time":0.709432373,"remaining_time":1.842482638},
{"learn":[0.4363309817],"iteration":278,"passed_time":0.7149345642,"remaining_time":1.847554913},
{"learn":[0.435290535],"iteration":279,"passed_time":0.7169169175,"remaining_time":1.843500645},
{"learn":[0.4350080094],"iteration":280,"passed_time":0.7186943924,"remaining_time":1.838936897},
{"learn":[0.4346038705],"iteration":281,"passed_time":0.7203563222,"remaining_time":1.834098721},
{"learn":[0.4343654512],"iteration":282,"passed_time":0.7221394985,"remaining_time":1.829590178},
{"learn":[0.4338282849],"iteration":283,"passed_time":0.72461303,"remaining_time":1.826841301},
{"learn":[0.4334660344],"iteration":284,"passed_time":0.7274447189,"remaining_time":1.824992891},
{"learn":[0.4333177431],"iteration":285,"passed_time":0.7294049752,"remaining_time":1.820962071},
{"learn":[0.4329702123],"iteration":286,"passed_time":0.731133942,"remaining_time":1.816371082},
{"learn":[0.4325991833],"iteration":287,"passed_time":0.7327522,"remaining_time":1.811526272},
{"learn":[0.4320762716],"iteration":288,"passed_time":0.7346124927,"remaining_time":1.807299247},
{"learn":[0.4318125236],"iteration":289,"passed_time":0.7366989155,"remaining_time":1.803642172},
{"learn":[0.4314171348],"iteration":290,"passed_time":0.7387213898,"remaining_time":1.799840087},
{"learn":[0.4310205733],"iteration":291,"passed_time":0.7410310678,"remaining_time":1.796746562},
{"learn":[0.4309081633],"iteration":292,"passed_time":0.7431127498,"remaining_time":1.793108239},
{"learn":[0.4306482902],"iteration":293,"passed_time":0.7449976649,"remaining_time":1.789007998},
{"learn":[0.4303111666],"iteration":294,"passed_time":0.7469612837,"remaining_time":1.785110864},
{"learn":[0.4300949605],"iteration":295,"passed_time":0.7485933742,"remaining_time":1.780438295},
{"learn":[0.4298863117],"iteration":296,"passed_time":0.7503292062,"remaining_time":1.776031757},
{"learn":[0.4294220277],"iteration":297,"passed_time":0.7520136501,"remaining_time":1.771522088},
{"learn":[0.4292865992],"iteration":298,"passed_time":0.7543949135,"remaining_time":1.768664998},
{"learn":[0.4290585227],"iteration":299,"passed_time":0.7572223005,"remaining_time":1.766852035},
{"learn":[0.4287079558],"iteration":300,"passed_time":0.7592148074,"remaining_time":1.763093523},
{"learn":[0.4284405645],"iteration":301,"passed_time":0.7610926404,"remaining_time":1.759081666},
{"learn":[0.4279992141],"iteration":302,"passed_time":0.7632234967,"remaining_time":1.755665931},
{"learn":[0.4276306806],"iteration":303,"passed_time":0.7649077938,"remaining_time":1.751236265},
{"learn":[0.4274253755],"iteration":304,"passed_time":0.7667768334,"remaining_time":1.747245571},
{"learn":[0.4270608833],"iteration":305,"passed_time":0.7697552148,"remaining_time":1.745784703},
{"learn":[0.4270089214],"iteration":306,"passed_time":0.7717813116,"remaining_time":1.742164329},
{"learn":[0.4266682788],"iteration":307,"passed_time":0.7737437291,"remaining_time":1.738411236},
{"learn":[0.4264773987],"iteration":308,"passed_time":0.7754609743,"remaining_time":1.734121467},
{"learn":[0.4263286132],"iteration":309,"passed_time":0.7771023504,"remaining_time":1.729679425},
{"learn":[0.426222438],"iteration":310,"passed_time":0.7789784071,"remaining_time":1.725775313},
{"learn":[0.4259975925],"iteration":311,"passed_time":0.7811546523,"remaining_time":1.722546156},
{"learn":[0.4256911069],"iteration":312,"passed_time":0.7835342214,"remaining_time":1.71977},
{"learn":[0.4253962895],"iteration":313,"passed_time":0.7865807224,"remaining_time":1.718453425},
{"learn":[0.4250369033],"iteration":314,"passed_time":0.7901947876,"remaining_time":1.718360094},
{"learn":[0.4246240262],"iteration":315,"passed_time":0.792334495,"remaining_time":1.715053147},
{"learn":[0.4241140666],"iteration":316,"passed_time":0.7940104182,"remaining_time":1.710754308},
{"learn":[0.42377529],"iteration":317,"passed_time":0.7956023691,"remaining_time":1.706291873},
{"learn":[0.4234254319],"iteration":318,"passed_time":0.7973195758,"remaining_time":1.702114831},
{"learn":[0.4230295272],"iteration":319,"passed_time":0.7996052882,"remaining_time":1.699161238},
{"learn":[0.4226228183],"iteration":320,"passed_time":0.8022123122,"remaining_time":1.696891464},
{"learn":[0.422441729],"iteration":321,"passed_time":0.8043381223,"remaining_time":1.693606357},
{"learn":[0.4221419858],"iteration":322,"passed_time":0.8064812859,"remaining_time":1.6903648},
{"learn":[0.4217742045],"iteration":323,"passed_time":0.8083737726,"remaining_time":1.686607007},
{"learn":[0.4215579783],"iteration":324,"passed_time":0.8100150479,"remaining_time":1.682338946},
{"learn":[0.4212923397],"iteration":325,"passed_time":0.8115831622,"remaining_time":1.67793574},
{"learn":[0.4209302445],"iteration":326,"passed_time":0.8143839875,"remaining_time":1.676086922},
{"learn":[0.4206413708],"iteration":327,"passed_time":0.8183584825,"remaining_time":1.676636891},
{"learn":[0.4202082623],"iteration":328,"passed_time":0.8205828902,"remaining_time":1.673590028},
{"learn":[0.4199570665],"iteration":329,"passed_time":0.8230176829,"remaining_time":1.670975296},
{"learn":[0.4197751543],"iteration":330,"passed_time":0.8247226428,"remaining_time":1.66688655},
{"learn":[0.4194444338],"iteration":331,"passed_time":0.8265201964,"remaining_time":1.662998468},
{"learn":[0.4190472503],"iteration":332,"passed_time":0.8308885698,"remaining_time":1.6642723},
{"learn":[0.4189040229],"iteration":333,"passed_time":0.8326554702,"remaining_time":1.660324979},
{"learn":[0.4185448193],"iteration":334,"passed_time":0.8346587101,"remaining_time":1.656859827},
{"learn":[0.4182879187],"iteration":335,"passed_time":0.8371451,"remaining_time":1.654358174},
{"learn":[0.4178992053],"iteration":336,"passed_time":0.8390259331,"remaining_time":1.650665263},
{"learn":[0.417554403],"iteration":337,"passed_time":0.8409141744,"remaining_time":1.646997584},
{"learn":[0.4171742609],"iteration":338,"passed_time":0.8469853249,"remaining_time":1.65149646},
{"learn":[0.4170014375],"iteration":339,"passed_time":0.8496492153,"remaining_time":1.649319065},
{"learn":[0.4166268414],"iteration":340,"passed_time":0.8520133575,"remaining_time":1.646559538},
{"learn":[0.4163740669],"iteration":341,"passed_time":0.853593213,"remaining_time":1.642293375},
{"learn":[0.4161943433],"iteration":342,"passed_time":0.8554589814,"remaining_time":1.638590527},
{"learn":[0.4159701203],"iteration":343,"passed_time":0.8571507906,"remaining_time":1.634566624},
{"learn":[0.4156826113],"iteration":344,"passed_time":0.8619684683,"remaining_time":1.63649086},
{"learn":[0.4152930295],"iteration":345,"passed_time":0.8638883536,"remaining_time":1.632898795},
{"learn":[0.4150889811],"iteration":346,"passed_time":0.8657615644,"remaining_time":1.629228535},
{"learn":[0.4148134115],"iteration":347,"passed_time":0.8676573836,"remaining_time":1.62561096},
{"learn":[0.4147196236],"iteration":348,"passed_time":0.8695396864,"remaining_time":1.62197804},
{"learn":[0.4145871554],"iteration":349,"passed_time":0.8751740053,"remaining_time":1.625323153},
{"learn":[0.4144202432],"iteration":350,"passed_time":0.8769861402,"remaining_time":1.621549872},
{"learn":[0.4140809112],"iteration":351,"passed_time":0.8788661339,"remaining_time":1.617912656},
{"learn":[0.4136675863],"iteration":352,"passed_time":0.8804484801,"remaining_time":1.613739849},
{"learn":[0.4132686484],"iteration":353,"passed_time":0.8821274256,"remaining_time":1.609757957},
{"learn":[0.4130784885],"iteration":354,"passed_time":0.8841488102,"remaining_time":1.606411219},
{"learn":[0.4127993059],"iteration":355,"passed_time":0.8886244051,"remaining_time":1.607511564},
{"learn":[0.4124895606],"iteration":356,"passed_time":0.8915404785,"remaining_time":1.605771786},
{"learn":[0.4122662714],"iteration":357,"passed_time":0.8935787079,"remaining_time":1.602451202},
{"learn":[0.4121296343],"iteration":358,"passed_time":0.8953804543,"remaining_time":1.598715519},
{"learn":[0.4120235205],"iteration":359,"passed_time":0.8973442222,"remaining_time":1.595278617},
{"learn":[0.4116887769],"iteration":360,"passed_time":0.8990356352,"remaining_time":1.591367786},
{"learn":[0.4115003396],"iteration":361,"passed_time":0.9007890423,"remaining_time":1.587578478},
{"learn":[0.411085888],"iteration":362,"passed_time":0.9070601667,"remaining_time":1.591728171},
{"learn":[0.4109901355],"iteration":363,"passed_time":0.9085526993,"remaining_time":1.5874712},
{"learn":[0.4109208574],"iteration":364,"passed_time":0.9099404406,"remaining_time":1.583047068},
{"learn":[0.4105007413],"iteration":365,"passed_time":0.9117226945,"remaining_time":1.579322919},
{"learn":[0.4102337987],"iteration":366,"passed_time":0.9140938503,"remaining_time":1.576625088},
{"learn":[0.40999078],"iteration":367,"passed_time":0.9159930757,"remaining_time":1.573118543},
{"learn":[0.4094313478],"iteration":368,"passed_time":0.9222124176,"remaining_time":1.577008226},
{"learn":[0.4090530122],"iteration":369,"passed_time":0.924274664,"remaining_time":1.573764968},
{"learn":[0.4088404373],"iteration":370,"passed_time":0.9259487481,"remaining_time":1.56986998},
{"learn":[0.4085678683],"iteration":371,"passed_time":0.9277062064,"remaining_time":1.566127682},
{"learn":[0.4082650072],"iteration":372,"passed_time":0.929501294,"remaining_time":1.56245928},
{"learn":[0.4079764086],"iteration":373,"passed_time":0.9314876252,"remaining_time":1.559120998},
{"learn":[0.4078680886],"iteration":374,"passed_time":0.9345104141,"remaining_time":1.557517357},
{"learn":[0.4077242528],"iteration":375,"passed_time":0.9374483194,"remaining_time":1.555765296},
{"learn":[0.4074272124],"iteration":376,"passed_time":0.9399650231,"remaining_time":1.5533109},
{"learn":[0.4070887182],"iteration":377,"passed_time":0.9416657235,"remaining_time":1.549513439},
{"learn":[0.4068114947],"iteration":378,"passed_time":0.9432704881,"remaining_time":1.54556985},
{"learn":[0.4065835585],"iteration":379,"passed_time":0.9447897584,"remaining_time":1.541499079},
{"learn":[0.4061937546],"iteration":380,"passed_time":0.9464363031,"remaining_time":1.537648482},
{"learn":[0.4058874158],"iteration":381,"passed_time":0.94999824,"remaining_time":1.536908147},
{"learn":[0.4057320118],"iteration":382,"passed_time":0.9525839625,"remaining_time":1.53458043},
{"learn":[0.4053043168],"iteration":383,"passed_time":0.9545973233,"remaining_time":1.531333206},
{"learn":[0.4049021489],"iteration":384,"passed_time":0.9565449765,"remaining_time":1.52798743},
{"learn":[0.4044417917],"iteration":385,"passed_time":0.9583850001,"remaining_time":1.524477694},
{"learn":[0.4043904669],"iteration":386,"passed_time":0.95943822,"remaining_time":1.519730307},
{"learn":[0.4041274028],"iteration":387,"passed_time":0.9612261903,"remaining_time":1.516160898},
{"learn":[0.4035436915],"iteration":388,"passed_time":0.9638180814,"remaining_time":1.513863362},
{"learn":[0.4033205381],"iteration":389,"passed_time":0.9664993024,"remaining_time":1.511704037},
{"learn":[0.4029830014],"iteration":390,"passed_time":0.9689263393,"remaining_time":1.50914614},
{"learn":[0.4025214488],"iteration":391,"passed_time":0.9713174002,"remaining_time":1.50653311},
{"learn":[0.4020845489],"iteration":392,"passed_time":0.9732953516,"remaining_time":1.503283151},
{"learn":[0.4018094632],"iteration":393,"passed_time":0.9751068455,"remaining_time":1.499783625},
{"learn":[0.4015593514],"iteration":394,"passed_time":0.9796962342,"remaining_time":1.500547397},
{"learn":[0.4011073705],"iteration":395,"passed_time":0.9824643953,"remaining_time":1.4985063},
{"learn":[0.4008892393],"iteration":396,"passed_time":0.9842702826,"remaining_time":1.494999951},
{"learn":[0.4004877968],"iteration":397,"passed_time":0.9864559991,"remaining_time":1.492076662},
{"learn":[0.4001475711],"iteration":398,"passed_time":0.9891822643,"remaining_time":1.48997128},
{"learn":[0.4000103071],"iteration":399,"passed_time":0.9919947524,"remaining_time":1.487992129},
{"learn":[0.3998330747],"iteration":400,"passed_time":0.9958581097,"remaining_time":1.487578573},
{"learn":[0.3993994158],"iteration":401,"passed_time":0.997878358,"remaining_time":1.484406115},
{"learn":[0.3992065014],"iteration":402,"passed_time":1.001292081,"remaining_time":1.483303654},
{"learn":[0.3990305728],"iteration":403,"passed_time":1.003432072,"remaining_time":1.48031068},
{"learn":[0.3988223078],"iteration":404,"passed_time":1.005085291,"remaining_time":1.476606785},
{"learn":[0.3985278257],"iteration":405,"passed_time":1.007344964,"remaining_time":1.473800268},
{"learn":[0.3980760254],"iteration":406,"passed_time":1.009753502,"remaining_time":1.471213333},
{"learn":[0.3979174782],"iteration":407,"passed_time":1.012001632,"remaining_time":1.468394525},
{"learn":[0.3974806201],"iteration":408,"passed_time":1.013869551,"remaining_time":1.465029106},
{"learn":[0.3972673147],"iteration":409,"passed_time":1.015805991,"remaining_time":1.461769597},
{"learn":[0.3970697494],"iteration":410,"passed_time":1.01754669,"remaining_time":1.45823601},
{"learn":[0.3967786294],"iteration":411,"passed_time":1.019410363,"remaining_time":1.454886635},
{"learn":[0.3966396984],"iteration":412,"passed_time":1.021173914,"remaining_time":1.45140215},
{"learn":[0.396466204],"iteration":413,"passed_time":1.024454282,"remaining_time":1.450072969},
{"learn":[0.3962636953],"iteration":414,"passed_time":1.027234314,"remaining_time":1.448029094},
{"learn":[0.3960073839],"iteration":415,"passed_time":1.029063021,"remaining_time":1.444646165},
{"learn":[0.3959767088],"iteration":416,"passed_time":1.029987736,"remaining_time":1.440006835},
{"learn":[0.3956066504],"iteration":417,"passed_time":1.031784316,"remaining_time":1.436599215},
{"learn":[0.395352082],"iteration":418,"passed_time":1.03344306,"remaining_time":1.433008158},
{"learn":[0.3950893898],"iteration":419,"passed_time":1.036160266,"remaining_time":1.430887986},
{"learn":[0.3947637081],"iteration":420,"passed_time":1.039517576,"remaining_time":1.429645312},
{"learn":[0.3944604222],"iteration":421,"passed_time":1.041970704,"remaining_time":1.427154188},
{"learn":[0.3939437808],"iteration":422,"passed_time":1.043675099,"remaining_time":1.42364192},
{"learn":[0.3938799592],"iteration":423,"passed_time":1.045360236,"remaining_time":1.420112019},
{"learn":[0.3937531396],"iteration":424,"passed_time":1.047092186,"remaining_time":1.416654133},
{"learn":[0.3935812765],"iteration":425,"passed_time":1.048949604,"remaining_time":1.41337341},
{"learn":[0.3933468433],"iteration":426,"passed_time":1.050738522,"remaining_time":1.410007431},
{"learn":[0.3930407743],"iteration":427,"passed_time":1.053694446,"remaining_time":1.408208466},
{"learn":[0.3928527113],"iteration":428,"passed_time":1.056327727,"remaining_time":1.405974666},
{"learn":[0.392704885],"iteration":429,"passed_time":1.058352073,"remaining_time":1.402931818},
{"learn":[0.3923022759],"iteration":430,"passed_time":1.060029687,"remaining_time":1.399435944},
{"learn":[0.3918477581],"iteration":431,"passed_time":1.061875512,"remaining_time":1.396169655},
{"learn":[0.3914846349],"iteration":432,"passed_time":1.063608453,"remaining_time":1.392762108},
{"learn":[0.3914808744],"iteration":433,"passed_time":1.064352307,"remaining_time":1.388072364},
{"learn":[0.3912661447],"iteration":434,"passed_time":1.06644916,"remaining_time":1.385158105},
{"learn":[0.391029297],"iteration":435,"passed_time":1.069517051,"remaining_time":1.383503708},
{"learn":[0.3906663338],"iteration":436,"passed_time":1.074769301,"remaining_time":1.384657017},
{"learn":[0.3903509354],"iteration":437,"passed_time":1.077254244,"remaining_time":1.382230331},
{"learn":[0.3901591541],"iteration":438,"passed_time":1.078960692,"remaining_time":1.378808538},
{"learn":[0.3899868448],"iteration":439,"passed_time":1.080522804,"remaining_time":1.375210842},
{"learn":[0.3898335768],"iteration":440,"passed_time":1.082363947,"remaining_time":1.371976069},
{"learn":[0.389481124],"iteration":441,"passed_time":1.086856246,"remaining_time":1.372094537},
{"learn":[0.3892951012],"iteration":442,"passed_time":1.088617924,"remaining_time":1.36875888},
{"learn":[0.389197267],"iteration":443,"passed_time":1.090548014,"remaining_time":1.365641206},
{"learn":[0.3890070323],"iteration":444,"passed_time":1.092312472,"remaining_time":1.362322297},
{"learn":[0.3888723522],"iteration":445,"passed_time":1.093850478,"remaining_time":1.358729069},
{"learn":[0.3886495659],"iteration":446,"passed_time":1.095833392,"remaining_time":1.355695449},
{"learn":[0.3882988412],"iteration":447,"passed_time":1.097519808,"remaining_time":1.352301192},
{"learn":[0.3877675521],"iteration":448,"passed_time":1.100886233,"remaining_time":1.350976202},
{"learn":[0.3875859085],"iteration":449,"passed_time":1.102992824,"remaining_time":1.348102341},
{"learn":[0.3872670732],"iteration":450,"passed_time":1.105005406,"remaining_time":1.345117446},
{"learn":[0.3871368325],"iteration":451,"passed_time":1.109360436,"remaining_time":1.344976811},
{"learn":[0.3870718562],"iteration":452,"passed_time":1.111196936,"remaining_time":1.341776433},
{"learn":[0.3869138956],"iteration":453,"passed_time":1.113322982,"remaining_time":1.338930283},
{"learn":[0.3867507056],"iteration":454,"passed_time":1.11663668,"remaining_time":1.337509869},
{"learn":[0.3866880957],"iteration":455,"passed_time":1.118991556,"remaining_time":1.334937295},
{"learn":[0.3863870894],"iteration":456,"passed_time":1.120778467,"remaining_time":1.331690826},
{"learn":[0.3862025102],"iteration":457,"passed_time":1.122645462,"remaining_time":1.328545503},
{"learn":[0.3860772054],"iteration":458,"passed_time":1.124430608,"remaining_time":1.325309279},
{"learn":[0.3857111724],"iteration":459,"passed_time":1.126233229,"remaining_time":1.322099878},
{"learn":[0.3852963091],"iteration":460,"passed_time":1.128684543,"remaining_time":1.319655029},
{"learn":[0.3850530476],"iteration":461,"passed_time":1.130934663,"remaining_time":1.316975863},
{"learn":[0.3847889089],"iteration":462,"passed_time":1.132975213,"remaining_time":1.314055485},
{"learn":[0.3845591764],"iteration":463,"passed_time":1.134893578,"remaining_time":1.310997754},
{"learn":[0.3844158904],"iteration":464,"passed_time":1.136604292,"remaining_time":1.307706013},
{"learn":[0.3841584931],"iteration":465,"passed_time":1.138400192,"remaining_time":1.304518675},
{"learn":[0.3840176217],"iteration":466,"passed_time":1.140279855,"remaining_time":1.301432897},
{"learn":[0.3837985886],"iteration":467,"passed_time":1.143541299,"remaining_time":1.299923015},
{"learn":[0.3836955075],"iteration":468,"passed_time":1.146007202,"remaining_time":1.297504956},
{"learn":[0.3834905595],"iteration":469,"passed_time":1.148167437,"remaining_time":1.294742003},
{"learn":[0.3830096564],"iteration":470,"passed_time":1.149922333,"remaining_time":1.291526357},
{"learn":[0.3826298374],"iteration":471,"passed_time":1.15163938,"remaining_time":1.288274561},
{"learn":[0.3824156212],"iteration":472,"passed_time":1.153345541,"remaining_time":1.285017125},
{"learn":[0.382026669],"iteration":473,"passed_time":1.155109692,"remaining_time":1.281830586},
{"learn":[0.3818956827],"iteration":474,"passed_time":1.15670397,"remaining_time":1.278462283},
{"learn":[0.3816482278],"iteration":475,"passed_time":1.159137889,"remaining_time":1.276025743},
{"learn":[0.3814506591],"iteration":476,"passed_time":1.161536438,"remaining_time":1.273550435},
{"learn":[0.3810001583],"iteration":477,"passed_time":1.163400546,"remaining_time":1.27049181},
{"learn":[0.380650254],"iteration":478,"passed_time":1.165721387,"remaining_time":1.267934953},
{"learn":[0.3804984017],"iteration":479,"passed_time":1.167788406,"remaining_time":1.265104107},
{"learn":[0.3801901964],"iteration":480,"passed_time":1.169696389,"remaining_time":1.262104835},
{"learn":[0.3798018075],"iteration":481,"passed_time":1.171628158,"remaining_time":1.259135656},
{"learn":[0.3794897719],"iteration":482,"passed_time":1.173940516,"remaining_time":1.25657815},
{"learn":[0.3792799228],"iteration":483,"passed_time":1.179167059,"remaining_time":1.257128517},
{"learn":[0.3788598237],"iteration":484,"passed_time":1.180899089,"remaining_time":1.253944393},
{"learn":[0.378404543],"iteration":485,"passed_time":1.182989984,"remaining_time":1.251145786},
{"learn":[0.3782460219],"iteration":486,"passed_time":1.184767927,"remaining_time":1.248020424},
{"learn":[0.378056491],"iteration":487,"passed_time":1.186451805,"remaining_time":1.244801894},
{"learn":[0.3776955117],"iteration":488,"passed_time":1.18809258,"remaining_time":1.241544598},
{"learn":[0.377448416],"iteration":489,"passed_time":1.191740925,"remaining_time":1.240383412},
{"learn":[0.3772629208],"iteration":490,"passed_time":1.193931079,"remaining_time":1.237700446},
{"learn":[0.3769071789],"iteration":491,"passed_time":1.195931738,"remaining_time":1.234823827},
{"learn":[0.3766719108],"iteration":492,"passed_time":1.197827663,"remaining_time":1.231843053},
{"learn":[0.3764825462],"iteration":493,"passed_time":1.199508233,"remaining_time":1.228646085},
{"learn":[0.3763855856],"iteration":494,"passed_time":1.201183897,"remaining_time":1.225450239},
{"learn":[0.3761541365],"iteration":495,"passed_time":1.202792959,"remaining_time":1.222192846},
{"learn":[0.3759588632],"iteration":496,"passed_time":1.204972321,"remaining_time":1.219519271},
{"learn":[0.3756158301],"iteration":497,"passed_time":1.20725563,"remaining_time":1.216952462},
{"learn":[0.375230872],"iteration":498,"passed_time":1.209204044,"remaining_time":1.214050553},
{"learn":[0.375000564],"iteration":499,"passed_time":1.213508769,"remaining_time":1.213508769},
{"learn":[0.3749277759],"iteration":500,"passed_time":1.215639305,"remaining_time":1.210786454},
{"learn":[0.3747078064],"iteration":501,"passed_time":1.217352441,"remaining_time":1.207652421},
{"learn":[0.3745008989],"iteration":502,"passed_time":1.220153579,"remaining_time":1.205599063},
{"learn":[0.3743779579],"iteration":503,"passed_time":1.22302652,"remaining_time":1.203613401},
{"learn":[0.3740285807],"iteration":504,"passed_time":1.224834784,"remaining_time":1.20058063},
{"learn":[0.3739139131],"iteration":505,"passed_time":1.226647357,"remaining_time":1.197556906},
{"learn":[0.3737586392],"iteration":506,"passed_time":1.228268345,"remaining_time":1.194351665},
{"learn":[0.3735965121],"iteration":507,"passed_time":1.229750574,"remaining_time":1.191018273},
{"learn":[0.3734355153],"iteration":508,"passed_time":1.231428217,"remaining_time":1.187880658},
{"learn":[0.373095847],"iteration":509,"passed_time":1.233780961,"remaining_time":1.185397394},
{"learn":[0.3727159165],"iteration":510,"passed_time":1.236468488,"remaining_time":1.183235011},
{"learn":[0.372346408],"iteration":511,"passed_time":1.238550921,"remaining_time":1.180493846},
{"learn":[0.3720899981],"iteration":512,"passed_time":1.24070959,"remaining_time":1.177827623},
{"learn":[0.3718199927],"iteration":513,"passed_time":1.242309914,"remaining_time":1.174635444},
{"learn":[0.3717144529],"iteration":514,"passed_time":1.243849532,"remaining_time":1.171392278},
{"learn":[0.371470566],"iteration":515,"passed_time":1.245853721,"remaining_time":1.168591475},
{"learn":[0.3713498713],"iteration":516,"passed_time":1.247799901,"remaining_time":1.165739559},
{"learn":[0.3711206813],"iteration":517,"passed_time":1.254396823,"remaining_time":1.167218666},
{"learn":[0.3707807788],"iteration":518,"passed_time":1.256780556,"remaining_time":1.164761941},
{"learn":[0.370594931],"iteration":519,"passed_time":1.258984922,"remaining_time":1.162139928},
{"learn":[0.3704475558],"iteration":520,"passed_time":1.260800969,"remaining_time":1.159162503},
{"learn":[0.3702842832],"iteration":521,"passed_time":1.262412365,"remaining_time":1.156002127},
{"learn":[0.3700642853],"iteration":522,"passed_time":1.264637168,"remaining_time":1.15340713},
{"learn":[0.3697392513],"iteration":523,"passed_time":1.267744041,"remaining_time":1.151614815},
{"learn":[0.3694842051],"iteration":524,"passed_time":1.269548324,"remaining_time":1.148638959},
{"learn":[0.3693093627],"iteration":525,"passed_time":1.271375407,"remaining_time":1.145688104},
{"learn":[0.3690540545],"iteration":526,"passed_time":1.273213218,"remaining_time":1.142751143},
{"learn":[0.3689482702],"iteration":527,"passed_time":1.274717614,"remaining_time":1.139520291},
{"learn":[0.3688155206],"iteration":528,"passed_time":1.276824304,"remaining_time":1.136832225},
{"learn":[0.3686091485],"iteration":529,"passed_time":1.27867867,"remaining_time":1.133922594},
{"learn":[0.3682142149],"iteration":530,"passed_time":1.282173171,"remaining_time":1.132465569},
{"learn":[0.3681062676],"iteration":531,"passed_time":1.284214518,"remaining_time":1.129722546},
{"learn":[0.3678471127],"iteration":532,"passed_time":1.286006894,"remaining_time":1.126764014},
{"learn":[0.3674620939],"iteration":533,"passed_time":1.288141197,"remaining_time":1.124108235},
{"learn":[0.3671884168],"iteration":534,"passed_time":1.289950364,"remaining_time":1.121171812},
{"learn":[0.3669074946],"iteration":535,"passed_time":1.292957438,"remaining_time":1.119276588},
{"learn":[0.3666135774],"iteration":536,"passed_time":1.296673544,"remaining_time":1.117988549},
{"learn":[0.3665050212],"iteration":537,"passed_time":1.299468338,"remaining_time":1.11590032},
{"learn":[0.3663542873],"iteration":538,"passed_time":1.301202264,"remaining_time":1.112902122},
{"learn":[0.3662181192],"iteration":539,"passed_time":1.303063051,"remaining_time":1.110016673},
{"learn":[0.3660107591],"iteration":540,"passed_time":1.304938912,"remaining_time":1.107147802},
{"learn":[0.3659214558],"iteration":541,"passed_time":1.306706724,"remaining_time":1.104191291},
{"learn":[0.365424279],"iteration":542,"passed_time":1.308582506,"remaining_time":1.101330028},
{"learn":[0.3651618365],"iteration":543,"passed_time":1.311814057,"remaining_time":1.099608842},
{"learn":[0.3649592446],"iteration":544,"passed_time":1.314026771,"remaining_time":1.097031525},
{"learn":[0.3646925792],"iteration":545,"passed_time":1.316208998,"remaining_time":1.094430192},
{"learn":[0.3644941273],"iteration":546,"passed_time":1.319112741,"remaining_time":1.092427919},
{"learn":[0.3643509698],"iteration":547,"passed_time":1.321037727,"remaining_time":1.08961506},
{"learn":[0.3642070182],"iteration":548,"passed_time":1.323026773,"remaining_time":1.08685806},
{"learn":[0.363850729],"iteration":549,"passed_time":1.325086477,"remaining_time":1.084161663},
{"learn":[0.363774801],"iteration":550,"passed_time":1.329388181,"remaining_time":1.083294544},
{"learn":[0.3635485614],"iteration":551,"passed_time":1.333266453,"remaining_time":1.082071324},
{"learn":[0.3631793919],"iteration":552,"passed_time":1.335629927,"remaining_time":1.079614064},
{"learn":[0.3630579513],"iteration":553,"passed_time":1.337766174,"remaining_time":1.076974213},
{"learn":[0.3627401399],"iteration":554,"passed_time":1.339369648,"remaining_time":1.073908997},
{"learn":[0.3622958483],"iteration":555,"passed_time":1.342004829,"remaining_time":1.071672921},
{"learn":[0.362147803],"iteration":556,"passed_time":1.344535581,"remaining_time":1.069352356},
{"learn":[0.3618696503],"iteration":557,"passed_time":1.346279687,"remaining_time":1.066407924},
{"learn":[0.3616767639],"iteration":558,"passed_time":1.349391587,"remaining_time":1.064546851},
{"learn":[0.3616396303],"iteration":559,"passed_time":1.351738387,"remaining_time":1.062080161},
{"learn":[0.3614926615],"iteration":560,"passed_time":1.354663153,"remaining_time":1.060066175},
{"learn":[0.36127673],"iteration":561,"passed_time":1.359216881,"remaining_time":1.059318495},
{"learn":[0.361069882],"iteration":562,"passed_time":1.361185591,"remaining_time":1.056550805},
{"learn":[0.3607268363],"iteration":563,"passed_time":1.363030484,"remaining_time":1.053690232},
{"learn":[0.3605754873],"iteration":564,"passed_time":1.365014088,"remaining_time":1.05094005},
{"learn":[0.3603813495],"iteration":565,"passed_time":1.367359136,"remaining_time":1.048469726},
{"learn":[0.3598553838],"iteration":566,"passed_time":1.369816977,"remaining_time":1.04608598},
{"learn":[0.3597346197],"iteration":567,"passed_time":1.374033636,"remaining_time":1.045039667},
{"learn":[0.3595822195],"iteration":568,"passed_time":1.376160453,"remaining_time":1.042399218},
{"learn":[0.3593069679],"iteration":569,"passed_time":1.378614669,"remaining_time":1.040007557},
{"learn":[0.3588907954],"iteration":570,"passed_time":1.380372805,"remaining_time":1.037092703},
{"learn":[0.3588022715],"iteration":571,"passed_time":1.382316688,"remaining_time":1.034320879},
{"learn":[0.3586039463],"iteration":572,"passed_time":1.384022512,"remaining_time":1.031374542},
{"learn":[0.3583815608],"iteration":573,"passed_time":1.389309771,"remaining_time":1.031090527},
{"learn":[0.358219717],"iteration":574,"passed_time":1.391215567,"remaining_time":1.028289767},
{"learn":[0.3580241279],"iteration":575,"passed_time":1.393380672,"remaining_time":1.025682995},
{"learn":[0.3576778623],"iteration":576,"passed_time":1.395083012,"remaining_time":1.022738499},
{"learn":[0.3575550561],"iteration":577,"passed_time":1.396889942,"remaining_time":1.019874663},
{"learn":[0.3575384495],"iteration":578,"passed_time":1.397846203,"remaining_time":1.016395944},
{"learn":[0.3574212807],"iteration":579,"passed_time":1.400443775,"remaining_time":1.014114458},
{"learn":[0.3572407616],"iteration":580,"passed_time":1.405826847,"remaining_time":1.013840704},
{"learn":[0.3569353037],"iteration":581,"passed_time":1.40758511,"remaining_time":1.010946007},
{"learn":[0.3567421213],"iteration":582,"passed_time":1.409751354,"remaining_time":1.008347023},
{"learn":[0.356467526],"iteration":583,"passed_time":1.411436413,"remaining_time":1.00540676},
{"learn":[0.3561004055],"iteration":584,"passed_time":1.41315155,"remaining_time":1.002492126},
{"learn":[0.3558401775],"iteration":585,"passed_time":1.414960714,"remaining_time":0.9996480127},
{"learn":[0.3557258009],"iteration":586,"passed_time":1.417048167,"remaining_time":0.9970032251},
{"learn":[0.3554034405],"iteration":587,"passed_time":1.419590663,"remaining_time":0.9946791718},
{"learn":[0.3551186505],"iteration":588,"passed_time":1.421979752,"remaining_time":0.9922473313},
{"learn":[0.3549543847],"iteration":589,"passed_time":1.42438767,"remaining_time":0.9898287198},
{"learn":[0.3545408683],"iteration":590,"passed_time":1.42601614,"remaining_time":0.9868707297},
{"learn":[0.3543190864],"iteration":591,"passed_time":1.427753142,"remaining_time":0.9839920305},
{"learn":[0.3540866171],"iteration":592,"passed_time":1.429870975,"remaining_time":0.9813785611},
{"learn":[0.3539733848],"iteration":593,"passed_time":1.431683921,"remaining_time":0.97855837},
{"learn":[0.3537870798],"iteration":594,"passed_time":1.434749186,"remaining_time":0.9765939835},
{"learn":[0.3534996281],"iteration":595,"passed_time":1.437082642,"remaining_time":0.9741298445},
{"learn":[0.3532020254],"iteration":596,"passed_time":1.439050141,"remaining_time":0.9714191068},
{"learn":[0.3530795334],"iteration":597,"passed_time":1.441247026,"remaining_time":0.9688650578},
{"learn":[0.3528052158],"iteration":598,"passed_time":1.443159615,"remaining_time":0.9661218789},
{"learn":[0.3525885863],"iteration":599,"passed_time":1.445440718,"remaining_time":0.9636271451},
{"learn":[0.3524975837],"iteration":600,"passed_time":1.448529882,"remaining_time":0.9616695892},
{"learn":[0.3520901492],"iteration":601,"passed_time":1.450483407,"remaining_time":0.9589574687},
{"learn":[0.3518669685],"iteration":602,"passed_time":1.452568899,"remaining_time":0.9563347478},
{"learn":[0.3514330441],"iteration":603,"passed_time":1.454332979,"remaining_time":0.9535030791},
{"learn":[0.3511500033],"iteration":604,"passed_time":1.4561278,"remaining_time":0.9506950098},
{"learn":[0.3509334962],"iteration":605,"passed_time":1.458905161,"remaining_time":0.9485290984},
{"learn":[0.3505871896],"iteration":606,"passed_time":1.461042331,"remaining_time":0.9459466822},
{"learn":[0.350317737],"iteration":607,"passed_time":1.463776831,"remaining_time":0.9437508517},
{"learn":[0.3500610194],"iteration":608,"passed_time":1.465877249,"remaining_time":0.9411461482},
{"learn":[0.3498395948],"iteration":609,"passed_time":1.468041705,"remaining_time":0.9385840407},
{"learn":[0.349624788],"iteration":610,"passed_time":1.470004764,"remaining_time":0.9358950133},
{"learn":[0.3495052851],"iteration":611,"passed_time":1.471809226,"remaining_time":0.9331078098},
{"learn":[0.3493485135],"iteration":612,"passed_time":1.474382839,"remaining_time":0.930809394},
{"learn":[0.349202917],"iteration":613,"passed_time":1.479100253,"remaining_time":0.9298578136},
{"learn":[0.3488987624],"iteration":614,"passed_time":1.48109512,"remaining_time":0.9271896278},
{"learn":[0.3488366014],"iteration":615,"passed_time":1.48324381,"remaining_time":0.9246195181},
{"learn":[0.3486248485],"iteration":616,"passed_time":1.48522199,"remaining_time":0.9219449305},
{"learn":[0.3484214695],"iteration":617,"passed_time":1.487121302,"remaining_time":0.9192238472},
{"learn":[0.3483952964],"iteration":618,"passed_time":1.488312627,"remaining_time":0.916069646},
{"learn":[0.3482251799],"iteration":619,"passed_time":1.494557023,"remaining_time":0.9160188205},
{"learn":[0.3479388447],"iteration":620,"passed_time":1.496787857,"remaining_time":0.9134985469},
{"learn":[0.3478605269],"iteration":621,"passed_time":1.4984586,"remaining_time":0.9106388275},
{"learn":[0.3477008231],"iteration":622,"passed_time":1.500071538,"remaining_time":0.9077479449},
{"learn":[0.347630568],"iteration":623,"passed_time":1.501893654,"remaining_time":0.9049872016},
{"learn":[0.3472618571],"iteration":624,"passed_time":1.503750121,"remaining_time":0.9022500729},
{"learn":[0.3471230538],"iteration":625,"passed_time":1.50544494,"remaining_time":0.8994191815},
{"learn":[0.3469767342],"iteration":626,"passed_time":1.512283189,"remaining_time":0.8996517218},
{"learn":[0.3465618861],"iteration":627,"passed_time":1.514245347,"remaining_time":0.8969733582},
{"learn":[0.3461232545],"iteration":628,"passed_time":1.515980188,"remaining_time":0.8941631949},
{"learn":[0.345971402],"iteration":629,"passed_time":1.517712518,"remaining_time":0.8913549709},
{"learn":[0.3458940689],"iteration":630,"passed_time":1.519503667,"remaining_time":0.8885845535},
{"learn":[0.3457159872],"iteration":631,"passed_time":1.521332825,"remaining_time":0.8858393664},
{"learn":[0.3455475377],"iteration":632,"passed_time":1.529262874,"remaining_time":0.8866342413},
{"learn":[0.3453192876],"iteration":633,"passed_time":1.531470817,"remaining_time":0.8840982949},
{"learn":[0.3451273784],"iteration":634,"passed_time":1.533528172,"remaining_time":0.8814768232},
{"learn":[0.3449840252],"iteration":635,"passed_time":1.535487138,"remaining_time":0.878800815},
{"learn":[0.3446351477],"iteration":636,"passed_time":1.537477634,"remaining_time":0.8761450253},
{"learn":[0.3443772499],"iteration":637,"passed_time":1.540431269,"remaining_time":0.8740378047},
{"learn":[0.3443665924],"iteration":638,"passed_time":1.541341752,"remaining_time":0.870773666},
{"learn":[0.3442402699],"iteration":639,"passed_time":1.543691933,"remaining_time":0.8683267121},
{"learn":[0.3440101142],"iteration":640,"passed_time":1.547076512,"remaining_time":0.8664593883},
{"learn":[0.3437687299],"iteration":641,"passed_time":1.549374857,"remaining_time":0.8639816181},
{"learn":[0.343428965],"iteration":642,"passed_time":1.55113367,"remaining_time":0.8612048524},
{"learn":[0.3432756038],"iteration":643,"passed_time":1.553404011,"remaining_time":0.8587140184},
{"learn":[0.3431075141],"iteration":644,"passed_time":1.556037929,"remaining_time":0.8564239766},
{"learn":[0.3429999058],"iteration":645,"passed_time":1.558096389,"remaining_time":0.853817526},
{"learn":[0.342738304],"iteration":646,"passed_time":1.560004241,"remaining_time":0.8511305983},
{"learn":[0.3424503696],"iteration":647,"passed_time":1.561728158,"remaining_time":0.84834616},
{"learn":[0.342309163],"iteration":648,"passed_time":1.564214409,"remaining_time":0.8459772842},
{"learn":[0.3420712807],"iteration":649,"passed_time":1.565828794,"remaining_time":0.8431385814},
{"learn":[0.3417895996],"iteration":650,"passed_time":1.568517712,"remaining_time":0.8408796949},
{"learn":[0.3415332651],"iteration":651,"passed_time":1.570681808,"remaining_time":0.83833937},
{"learn":[0.341148089],"iteration":652,"passed_time":1.572425546,"remaining_time":0.8355768216},
{"learn":[0.3410609344],"iteration":653,"passed_time":1.574278912,"remaining_time":0.8328753875},
{"learn":[0.3408591572],"iteration":654,"passed_time":1.576018505,"remaining_time":0.830116617},
{"learn":[0.340743641],"iteration":655,"passed_time":1.577604523,"remaining_time":0.8272804208},
{"learn":[0.3403073828],"iteration":656,"passed_time":1.579368862,"remaining_time":0.8245411259},
{"learn":[0.3401857908],"iteration":657,"passed_time":1.583314321,"remaining_time":0.8229384467},
{"learn":[0.3400409554],"iteration":658,"passed_time":1.586945464,"remaining_time":0.8211660139},
{"learn":[0.3399171715],"iteration":659,"passed_time":1.588876908,"remaining_time":0.8185123466},
{"learn":[0.3396737704],"iteration":660,"passed_time":1.59083867,"remaining_time":0.8158764134},
{"learn":[0.339579732],"iteration":661,"passed_time":1.592439433,"remaining_time":0.8130582001},
{"learn":[0.3393626495],"iteration":662,"passed_time":1.594233101,"remaining_time":0.8103417122},
{"learn":[0.3390404416],"iteration":663,"passed_time":1.596201832,"remaining_time":0.8077165898},
{"learn":[0.3389928569],"iteration":664,"passed_time":1.599033821,"remaining_time":0.805528316},
{"learn":[0.3388428572],"iteration":665,"passed_time":1.601637589,"remaining_time":0.8032236559},
{"learn":[0.3384731906],"iteration":666,"passed_time":1.604629665,"remaining_time":0.8011119619},
{"learn":[0.3382351865],"iteration":667,"passed_time":1.606452161,"remaining_time":0.7984163435},
{"learn":[0.3379665652],"iteration":668,"passed_time":1.608312899,"remaining_time":0.7957422565},
{"learn":[0.3377140811],"iteration":669,"passed_time":1.610098294,"remaining_time":0.793033488},
{"learn":[0.3375953385],"iteration":670,"passed_time":1.612019951,"remaining_time":0.7903942831},
{"learn":[0.3372702718],"iteration":671,"passed_time":1.615353675,"remaining_time":0.7884464368},
{"learn":[0.3371603554],"iteration":672,"passed_time":1.618072403,"remaining_time":0.786195655},
{"learn":[0.3370933848],"iteration":673,"passed_time":1.619281471,"remaining_time":0.7832132932},
{"learn":[0.3367910798],"iteration":674,"passed_time":1.621012943,"remaining_time":0.7804877135},
{"learn":[0.3367115412],"iteration":675,"passed_time":1.62273046,"remaining_time":0.7777583862},
{"learn":[0.3364099725],"iteration":676,"passed_time":1.624546374,"remaining_time":0.7750789937},
{"learn":[0.3362003368],"iteration":677,"passed_time":1.626411475,"remaining_time":0.7724255087},
{"learn":[0.335976708],"iteration":678,"passed_time":1.62978798,"remaining_time":0.7704888685},
{"learn":[0.3357216465],"iteration":679,"passed_time":1.632920727,"remaining_time":0.7684332833},
{"learn":[0.3354723182],"iteration":680,"passed_time":1.63513995,"remaining_time":0.7659466137},
{"learn":[0.3353539426],"iteration":681,"passed_time":1.636990305,"remaining_time":0.7632887345},
{"learn":[0.3352370755],"iteration":682,"passed_time":1.63859779,"remaining_time":0.7605204968},
{"learn":[0.335059351],"iteration":683,"passed_time":1.640174436,"remaining_time":0.7577414059},
{"learn":[0.3348478385],"iteration":684,"passed_time":1.642167681,"remaining_time":0.7551574005},
{"learn":[0.3345994175],"iteration":685,"passed_time":1.645214651,"remaining_time":0.7530574349},
{"learn":[0.3344166684],"iteration":686,"passed_time":1.647715997,"remaining_time":0.750706124},
{"learn":[0.334184312],"iteration":687,"passed_time":1.649537096,"remaining_time":0.7480458922},
{"learn":[0.3340781077],"iteration":688,"passed_time":1.651456491,"remaining_time":0.7454324653},
{"learn":[0.3337799923],"iteration":689,"passed_time":1.653376536,"remaining_time":0.7428213422},
{"learn":[0.333727334],"iteration":690,"passed_time":1.654473913,"remaining_time":0.7398443404},
{"learn":[0.3334572995],"iteration":691,"passed_time":1.656233771,"remaining_time":0.7371676321},
{"learn":[0.3330178399],"iteration":692,"passed_time":1.65895829,"remaining_time":0.7349209164},
{"learn":[0.3324835043],"iteration":693,"passed_time":1.663187702,"remaining_time":0.7333363642},
{"learn":[0.3323986528],"iteration":694,"passed_time":1.664962775,"remaining_time":0.7306671172},
{"learn":[0.3321540018],"iteration":695,"passed_time":1.666587645,"remaining_time":0.7279348335},
{"learn":[0.3318733097],"iteration":696,"passed_time":1.668147937,"remaining_time":0.7251776541},
{"learn":[0.3317878727],"iteration":697,"passed_time":1.669706447,"remaining_time":0.7224231333},
{"learn":[0.3316696485],"iteration":698,"passed_time":1.671174922,"remaining_time":0.7196332641},
{"learn":[0.3312878204],"iteration":699,"passed_time":1.673327884,"remaining_time":0.7171405219},
{"learn":[0.3309672403],"iteration":700,"passed_time":1.676201257,"remaining_time":0.7149560282},
{"learn":[0.3309059408],"iteration":701,"passed_time":1.6774556,"remaining_time":0.7120822916},
{"learn":[0.3307399518],"iteration":702,"passed_time":1.679161802,"remaining_time":0.7094040615},
{"learn":[0.33059549],"iteration":703,"passed_time":1.680695004,"remaining_time":0.706655854},
{"learn":[0.3304614334],"iteration":704,"passed_time":1.682153947,"remaining_time":0.7038800202},
{"learn":[0.3303954142],"iteration":705,"passed_time":1.683884098,"remaining_time":0.7012208566},
{"learn":[0.3303364729],"iteration":706,"passed_time":1.685634214,"remaining_time":0.698572595},
{"learn":[0.3300908178],"iteration":707,"passed_time":1.687453709,"remaining_time":0.6959554844},
{"learn":[0.3299381859],"iteration":708,"passed_time":1.690127512,"remaining_time":0.6936912637},
{"learn":[0.3297777363],"iteration":709,"passed_time":1.692522806,"remaining_time":0.6913121321},
{"learn":[0.3294624812],"iteration":710,"passed_time":1.694722062,"remaining_time":0.6888532714},
{"learn":[0.32933532],"iteration":711,"passed_time":1.696466347,"remaining_time":0.6862111065},
{"learn":[0.3290607693],"iteration":712,"passed_time":1.698251138,"remaining_time":0.6835877652},
{"learn":[0.3289190918],"iteration":713,"passed_time":1.699857914,"remaining_time":0.680895467},
{"learn":[0.3286439671],"iteration":714,"passed_time":1.701495896,"remaining_time":0.678218644},
{"learn":[0.3283087223],"iteration":715,"passed_time":1.707059034,"remaining_time":0.6771016281},
{"learn":[0.3281996777],"iteration":716,"passed_time":1.709461884,"remaining_time":0.674724844},
{"learn":[0.328075014],"iteration":717,"passed_time":1.711117764,"remaining_time":0.6720546092},
{"learn":[0.3278891577],"iteration":718,"passed_time":1.712796889,"remaining_time":0.6693962808},
{"learn":[0.327514506],"iteration":719,"passed_time":1.714579505,"remaining_time":0.6667809186},
{"learn":[0.3273343501],"iteration":720,"passed_time":1.716097162,"remaining_time":0.6640653374},
{"learn":[0.3271876293],"iteration":721,"passed_time":1.717778299,"remaining_time":0.661416021},
{"learn":[0.3270767765],"iteration":722,"passed_time":1.720665476,"remaining_time":0.6592314478},
{"learn":[0.3270676782],"iteration":723,"passed_time":1.722162498,"remaining_time":0.6565149856},
{"learn":[0.3269072237],"iteration":724,"passed_time":1.724167754,"remaining_time":0.6539946653},
{"learn":[0.3268015416],"iteration":725,"passed_time":1.725916885,"remaining_time":0.6513790998},
{"learn":[0.3267245711],"iteration":726,"passed_time":1.727760009,"remaining_time":0.6488012137},
{"learn":[0.3265344247],"iteration":727,"passed_time":1.729657637,"remaining_time":0.6462457104},
{"learn":[0.3264403641],"iteration":728,"passed_time":1.7329891,"remaining_time":0.6442250288},
{"learn":[0.3262761286],"iteration":729,"passed_time":1.736008474,"remaining_time":0.6420853261},
{"learn":[0.3260642991],"iteration":730,"passed_time":1.738031238,"remaining_time":0.6395764746},
{"learn":[0.3258447276],"iteration":731,"passed_time":1.739924525,"remaining_time":0.6370215475},
{"learn":[0.3257509285],"iteration":732,"passed_time":1.741717584,"remaining_time":0.6344319166},
{"learn":[0.3254157304],"iteration":733,"passed_time":1.743516826,"remaining_time":0.631846697},
{"learn":[0.3251707649],"iteration":734,"passed_time":1.745249705,"remaining_time":0.6292396897},
{"learn":[0.325026621],"iteration":735,"passed_time":1.747427005,"remaining_time":0.6267944692},
{"learn":[0.324851827],"iteration":736,"passed_time":1.750009642,"remaining_time":0.6244946212},
{"learn":[0.3247480522],"iteration":737,"passed_time":1.751953312,"remaining_time":0.6219671651},
{"learn":[0.3245533724],"iteration":738,"passed_time":1.753913166,"remaining_time":0.6194470045},
{"learn":[0.3242781427],"iteration":739,"passed_time":1.75567559,"remaining_time":0.6168589909},
{"learn":[0.3240327914],"iteration":740,"passed_time":1.757749969,"remaining_time":0.614382243},
{"learn":[0.323921997],"iteration":741,"passed_time":1.759468125,"remaining_time":0.6117827175},
{"learn":[0.3236017754],"iteration":742,"passed_time":1.762816345,"remaining_time":0.6097493951},
{"learn":[0.3233254136],"iteration":743,"passed_time":1.765193291,"remaining_time":0.6073783366},
{"learn":[0.3232044915],"iteration":744,"passed_time":1.767619338,"remaining_time":0.6050240688},
{"learn":[0.3229404071],"iteration":745,"passed_time":1.769762948,"remaining_time":0.6025734435},
{"learn":[0.3227282584],"iteration":746,"passed_time":1.771442884,"remaining_time":0.5999665993},
{"learn":[0.3225951245],"iteration":747,"passed_time":1.773191098,"remaining_time":0.5973852363},
{"learn":[0.3225059701],"iteration":748,"passed_time":1.774797534,"remaining_time":0.5947585863},
{"learn":[0.322406101],"iteration":749,"passed_time":1.77834581,"remaining_time":0.5927819368},
{"learn":[0.3220665807],"iteration":750,"passed_time":1.783532949,"remaining_time":0.5913444798},
{"learn":[0.3218539737],"iteration":751,"passed_time":1.78560939,"remaining_time":0.5888711817},
{"learn":[0.3216033094],"iteration":752,"passed_time":1.787215883,"remaining_time":0.5862447849},
{"learn":[0.3215689902],"iteration":753,"passed_time":1.788759169,"remaining_time":0.5836004716},
{"learn":[0.321496679],"iteration":754,"passed_time":1.791537713,"remaining_time":0.5813599202},
{"learn":[0.3213653649],"iteration":755,"passed_time":1.796416283,"remaining_time":0.5797957317},
{"learn":[0.3211456536],"iteration":756,"passed_time":1.798325051,"remaining_time":0.5772694683},
{"learn":[0.3209120123],"iteration":757,"passed_time":1.802103032,"remaining_time":0.5753416014},
{"learn":[0.320473277],"iteration":758,"passed_time":1.804056376,"remaining_time":0.5728294949},
{"learn":[0.32032548],"iteration":759,"passed_time":1.805702432,"remaining_time":0.5702218206},
{"learn":[0.3199332778],"iteration":760,"passed_time":1.809826435,"remaining_time":0.5683948987},
{"learn":[0.3196477078],"iteration":761,"passed_time":1.811815959,"remaining_time":0.5658952731},
{"learn":[0.319552221],"iteration":762,"passed_time":1.813553401,"remaining_time":0.5633186842},
{"learn":[0.3194176553],"iteration":763,"passed_time":1.815372218,"remaining_time":0.5607694285},
{"learn":[0.3191323981],"iteration":764,"passed_time":1.817553664,"remaining_time":0.5583334785},
{"learn":[0.3190317033],"iteration":765,"passed_time":1.820391199,"remaining_time":0.5560986169},
{"learn":[0.3188139257],"iteration":766,"passed_time":1.823052369,"remaining_time":0.5538086074},
{"learn":[0.3185854371],"iteration":767,"passed_time":1.825848007,"remaining_time":0.5515582522},
{"learn":[0.3184659548],"iteration":768,"passed_time":1.828118812,"remaining_time":0.549148824},
{"learn":[0.318377127],"iteration":769,"passed_time":1.829883493,"remaining_time":0.5465885759},
{"learn":[0.3182491096],"iteration":770,"passed_time":1.831664769,"remaining_time":0.5440353206},
{"learn":[0.3180424143],"iteration":771,"passed_time":1.833585254,"remaining_time":0.5415251786},
{"learn":[0.3179557898],"iteration":772,"passed_time":1.838243361,"remaining_time":0.5398204954},
{"learn":[0.3178578506],"iteration":773,"passed_time":1.840545668,"remaining_time":0.5374203112},
{"learn":[0.3174835553],"iteration":774,"passed_time":1.842332815,"remaining_time":0.5348708171},
{"learn":[0.3173950725],"iteration":775,"passed_time":1.844216488,"remaining_time":0.5323511511},
{"learn":[0.3172065652],"iteration":776,"passed_time":1.846066674,"remaining_time":0.5298235114},
{"learn":[0.3168943019],"iteration":777,"passed_time":1.847719061,"remaining_time":0.5272411716},
{"learn":[0.3166400123],"iteration":778,"passed_time":1.849552843,"remaining_time":0.5247126806},
{"learn":[0.3165471527],"iteration":779,"passed_time":1.851708405,"remaining_time":0.5222767296},
{"learn":[0.3162037269],"iteration":780,"passed_time":1.858219307,"remaining_time":0.5210627763},
{"learn":[0.3159623447],"iteration":781,"passed_time":1.860297277,"remaining_time":0.5185994966},
{"learn":[0.3157603733],"iteration":782,"passed_time":1.862747355,"remaining_time":0.5162403271},
{"learn":[0.3157191175],"iteration":783,"passed_time":1.864441367,"remaining_time":0.5136726215},
{"learn":[0.3155655175],"iteration":784,"passed_time":1.866292236,"remaining_time":0.5111501029},
{"learn":[0.3154267617],"iteration":785,"passed_time":1.870047032,"remaining_time":0.5091476652},
{"learn":[0.3152846463],"iteration":786,"passed_time":1.872646424,"remaining_time":0.5068280664},
{"learn":[0.3150797139],"iteration":787,"passed_time":1.879026259,"remaining_time":0.5055248311},
{"learn":[0.314799648],"iteration":788,"passed_time":1.881274619,"remaining_time":0.5031038589},
{"learn":[0.3146267578],"iteration":789,"passed_time":1.884352848,"remaining_time":0.5009039216},
{"learn":[0.3145572759],"iteration":790,"passed_time":1.887387291,"remaining_time":0.4986901945},
{"learn":[0.3143788597],"iteration":791,"passed_time":1.890022329,"remaining_time":0.4963695005},
{"learn":[0.3142527228],"iteration":792,"passed_time":1.892235328,"remaining_time":0.4939378473},
{"learn":[0.3140242411],"iteration":793,"passed_time":1.894738482,"remaining_time":0.4915820243},
{"learn":[0.3138054038],"iteration":794,"passed_time":1.896497772,"remaining_time":0.4890340166},
{"learn":[0.3135168906],"iteration":795,"passed_time":1.90102537,"remaining_time":0.4871974565},
{"learn":[0.3132244253],"iteration":796,"passed_time":1.904739922,"remaining_time":0.4851470568},
{"learn":[0.3129621713],"iteration":797,"passed_time":1.906853745,"remaining_time":0.4826872889},
{"learn":[0.3127911723],"iteration":798,"passed_time":1.908577463,"remaining_time":0.4801302503},
{"learn":[0.3126347139],"iteration":799,"passed_time":1.910565859,"remaining_time":0.4776414648},
{"learn":[0.3124826173],"iteration":800,"passed_time":1.912352546,"remaining_time":0.475103816},
{"learn":[0.3123122421],"iteration":801,"passed_time":1.915204369,"remaining_time":0.4728310039},
{"learn":[0.3121717033],"iteration":802,"passed_time":1.917346959,"remaining_time":0.4703827533},
{"learn":[0.311876394],"iteration":803,"passed_time":1.91978937,"remaining_time":0.468008354},
{"learn":[0.3118152248],"iteration":804,"passed_time":1.922186977,"remaining_time":0.4656229323},
{"learn":[0.3115013811],"iteration":805,"passed_time":1.923912926,"remaining_time":0.463075816},
{"learn":[0.3114027278],"iteration":806,"passed_time":1.925797232,"remaining_time":0.4605686069},
{"learn":[0.3112010842],"iteration":807,"passed_time":1.928111382,"remaining_time":0.4581650809},
{"learn":[0.3111084028],"iteration":808,"passed_time":1.931684764,"remaining_time":0.4560590728},
{"learn":[0.3109596536],"iteration":809,"passed_time":1.933680407,"remaining_time":0.4535793546},
{"learn":[0.3107102409],"iteration":810,"passed_time":1.935364355,"remaining_time":0.4510281912},
{"learn":[0.3106043654],"iteration":811,"passed_time":1.937056814,"remaining_time":0.4484811343},
{"learn":[0.3105117378],"iteration":812,"passed_time":1.93913439,"remaining_time":0.4460247612},
{"learn":[0.3104035337],"iteration":813,"passed_time":1.940956957,"remaining_time":0.4435110491},
{"learn":[0.3101387995],"iteration":814,"passed_time":1.944374585,"remaining_time":0.4413611022},
{"learn":[0.3099513048],"iteration":815,"passed_time":1.94687908,"remaining_time":0.4390021454},
{"learn":[0.3098305396],"iteration":816,"passed_time":1.948676018,"remaining_time":0.4364843468},
{"learn":[0.3096718948],"iteration":817,"passed_time":1.950252623,"remaining_time":0.4339192878},
{"learn":[0.3095334873],"iteration":818,"passed_time":1.95196424,"remaining_time":0.4313864804},
{"learn":[0.3092003387],"iteration":819,"passed_time":1.954590702,"remaining_time":0.4290564955},
{"learn":[0.308998337],"iteration":820,"passed_time":1.95648749,"remaining_time":0.4265667},
{"learn":[0.308858783],"iteration":821,"passed_time":1.959732848,"remaining_time":0.4243703735},
{"learn":[0.3087768096],"iteration":822,"passed_time":1.961794876,"remaining_time":0.4219170025},
{"learn":[0.3085048835],"iteration":823,"passed_time":1.963620214,"remaining_time":0.4194140263},
{"learn":[0.3083016539],"iteration":824,"passed_time":1.965344193,"remaining_time":0.4168911924},
{"learn":[0.3080571511],"iteration":825,"passed_time":1.966968682,"remaining_time":0.414349335},
{"learn":[0.3079332877],"iteration":826,"passed_time":1.9704217,"remaining_time":0.4121922057},
{"learn":[0.3078293959],"iteration":827,"passed_time":1.97284387,"remaining_time":0.4098178087},
{"learn":[0.3076907048],"iteration":828,"passed_time":1.976228968,"remaining_time":0.4076419222},
{"learn":[0.3075542953],"iteration":829,"passed_time":1.978404196,"remaining_time":0.4052153172},
{"learn":[0.307423482],"iteration":830,"passed_time":1.980026436,"remaining_time":0.4026768565},
{"learn":[0.3071391547],"iteration":831,"passed_time":1.981950265,"remaining_time":0.4002014958},
{"learn":[0.3070699841],"iteration":832,"passed_time":1.983908742,"remaining_time":0.3977344057},
{"learn":[0.3070104466],"iteration":833,"passed_time":1.985534362,"remaining_time":0.395202283},
{"learn":[0.3067233395],"iteration":834,"passed_time":1.993467377,"remaining_time":0.3939187032},
{"learn":[0.3065823201],"iteration":835,"passed_time":1.995447518,"remaining_time":0.3914514271},
{"learn":[0.3064011879],"iteration":836,"passed_time":1.997367164,"remaining_time":0.3889735336},
{"learn":[0.3062032834],"iteration":837,"passed_time":1.999166312,"remaining_time":0.3864736785},
{"learn":[0.3060488181],"iteration":838,"passed_time":2.001055195,"remaining_time":0.3839927133},
{"learn":[0.3059309612],"iteration":839,"passed_time":2.002646526,"remaining_time":0.3814564811},
{"learn":[0.3056286116],"iteration":840,"passed_time":2.006574186,"remaining_time":0.379364204},
{"learn":[0.3054165816],"iteration":841,"passed_time":2.011645281,"remaining_time":0.3774821311},
{"learn":[0.3053585237],"iteration":842,"passed_time":2.013982349,"remaining_time":0.3750833082},
{"learn":[0.3052180517],"iteration":843,"passed_time":2.015899422,"remaining_time":0.3726070023},
{"learn":[0.304919517],"iteration":844,"passed_time":2.017655391,"remaining_time":0.3701024682},
{"learn":[0.3045917872],"iteration":845,"passed_time":2.022598541,"remaining_time":0.3681798762},
{"learn":[0.3043217258],"iteration":846,"passed_time":2.024760136,"remaining_time":0.3657476987},
{"learn":[0.3041577775],"iteration":847,"passed_time":2.026619204,"remaining_time":0.3632619327},
{"learn":[0.3040475095],"iteration":848,"passed_time":2.028469387,"remaining_time":0.360776063},
{"learn":[0.3038575389],"iteration":849,"passed_time":2.03013583,"remaining_time":0.3582592641},
{"learn":[0.3036235521],"iteration":850,"passed_time":2.03214395,"remaining_time":0.3558042874},
{"learn":[0.3033244015],"iteration":851,"passed_time":2.034693877,"remaining_time":0.3534444763},
{"learn":[0.3031661544],"iteration":852,"passed_time":2.037285957,"remaining_time":0.3510914838},
{"learn":[0.3029339486],"iteration":853,"passed_time":2.039360424,"remaining_time":0.3486494401},
{"learn":[0.3026969799],"iteration":854,"passed_time":2.042619609,"remaining_time":0.3464091735},
{"learn":[0.3025675496],"iteration":855,"passed_time":2.044391672,"remaining_time":0.343916356},
{"learn":[0.3024670981],"iteration":856,"passed_time":2.046808681,"remaining_time":0.3415328371},
{"learn":[0.302233519],"iteration":857,"passed_time":2.050574527,"remaining_time":0.3393724741},
{"learn":[0.3019782327],"iteration":858,"passed_time":2.053263114,"remaining_time":0.3370315473},
{"learn":[0.3018677935],"iteration":859,"passed_time":2.055403418,"remaining_time":0.3346005564},
{"learn":[0.3018581945],"iteration":860,"passed_time":2.056405648,"remaining_time":0.3319865099},
{"learn":[0.3016458065],"iteration":861,"passed_time":2.058103737,"remaining_time":0.3294876053},
{"learn":[0.3014867573],"iteration":862,"passed_time":2.060047981,"remaining_time":0.3270296331},
{"learn":[0.3013649573],"iteration":863,"passed_time":2.064338006,"remaining_time":0.3249420936},
{"learn":[0.3011970033],"iteration":864,"passed_time":2.070685389,"remaining_time":0.323170552},
{"learn":[0.3010244379],"iteration":865,"passed_time":2.072555851,"remaining_time":0.320695709},
{"learn":[0.3008319203],"iteration":866,"passed_time":2.074500813,"remaining_time":0.3182336888},
{"learn":[0.3006928791],"iteration":867,"passed_time":2.076567484,"remaining_time":0.3157913685},
{"learn":[0.3002350287],"iteration":868,"passed_time":2.079828017,"remaining_time":0.3135298852},
{"learn":[0.300130687],"iteration":869,"passed_time":2.083798355,"remaining_time":0.311372168},
{"learn":[0.3000471006],"iteration":870,"passed_time":2.086149285,"remaining_time":0.3089704452},
{"learn":[0.2999068103],"iteration":871,"passed_time":2.088303847,"remaining_time":0.3065400142},
{"learn":[0.2997615356],"iteration":872,"passed_time":2.090118912,"remaining_time":0.3040608268},
{"learn":[0.299710186],"iteration":873,"passed_time":2.091796792,"remaining_time":0.3015633819},
{"learn":[0.2996331892],"iteration":874,"passed_time":2.095796981,"remaining_time":0.2993995686},
{"learn":[0.2992943484],"iteration":875,"passed_time":2.098336585,"remaining_time":0.2970248134},
{"learn":[0.2990974665],"iteration":876,"passed_time":2.100308485,"remaining_time":0.2945700612},
{"learn":[0.2988992978],"iteration":877,"passed_time":2.102107874,"remaining_time":0.2920924381},
{"learn":[0.298876987],"iteration":878,"passed_time":2.103740256,"remaining_time":0.2895933686},
{"learn":[0.2987139601],"iteration":879,"passed_time":2.110671551,"remaining_time":0.2878188478},
{"learn":[0.2983704733],"iteration":880,"passed_time":2.113197601,"remaining_time":0.2854375875},
{"learn":[0.2981866749],"iteration":881,"passed_time":2.115685431,"remaining_time":0.2830508853},
{"learn":[0.2978756108],"iteration":882,"passed_time":2.118606656,"remaining_time":0.2807213802},
{"learn":[0.2975681662],"iteration":883,"passed_time":2.120970628,"remaining_time":0.2783174127},
{"learn":[0.2974490879],"iteration":884,"passed_time":2.124756033,"remaining_time":0.2760982415},
{"learn":[0.2972088965],"iteration":885,"passed_time":2.13014308,"remaining_time":0.2740816153},
{"learn":[0.2971153018],"iteration":886,"passed_time":2.132237656,"remaining_time":0.2716379427},
{"learn":[0.2969860806],"iteration":887,"passed_time":2.133960915,"remaining_time":0.2691482235},
{"learn":[0.2968967098],"iteration":888,"passed_time":2.136394087,"remaining_time":0.266748868},
{"learn":[0.2967483222],"iteration":889,"passed_time":2.139741896,"remaining_time":0.2644624816},
{"learn":[0.296659364],"iteration":890,"passed_time":2.14235363,"remaining_time":0.2620836652},
{"learn":[0.2964527607],"iteration":891,"passed_time":2.144334424,"remaining_time":0.2596279347},
{"learn":[0.2963701546],"iteration":892,"passed_time":2.147755314,"remaining_time":0.2573458215},
{"learn":[0.2962505746],"iteration":893,"passed_time":2.149917949,"remaining_time":0.2549119716},
{"learn":[0.296002322],"iteration":894,"passed_time":2.151838115,"remaining_time":0.2524502816},
{"learn":[0.2959206873],"iteration":895,"passed_time":2.15390188,"remaining_time":0.2500064682},
{"learn":[0.2958298441],"iteration":896,"passed_time":2.157679388,"remaining_time":0.2477602864},
{"learn":[0.2956329721],"iteration":897,"passed_time":2.1597806,"remaining_time":0.2453202909},
{"learn":[0.2955306278],"iteration":898,"passed_time":2.16213516,"remaining_time":0.2429095119},
{"learn":[0.295134225],"iteration":899,"passed_time":2.165518706,"remaining_time":0.2406131895},
{"learn":[0.2948741099],"iteration":900,"passed_time":2.168034098,"remaining_time":0.2382190629},
{"learn":[0.2947766731],"iteration":901,"passed_time":2.170747793,"remaining_time":0.2358462125},
{"learn":[0.2944538167],"iteration":902,"passed_time":2.172497267,"remaining_time":0.2333690309},
{"learn":[0.2942505326],"iteration":903,"passed_time":2.174088169,"remaining_time":0.2308766197},
{"learn":[0.2940205685],"iteration":904,"passed_time":2.176091127,"remaining_time":0.2284294553},
{"learn":[0.2937118495],"iteration":905,"passed_time":2.178063558,"remaining_time":0.2259801043},
{"learn":[0.2935583859],"iteration":906,"passed_time":2.179965035,"remaining_time":0.2235245295},
{"learn":[0.2933364751],"iteration":907,"passed_time":2.182003029,"remaining_time":0.2210840074},
{"learn":[0.2932359097],"iteration":908,"passed_time":2.18664266,"remaining_time":0.2189048208},
{"learn":[0.2930599264],"iteration":909,"passed_time":2.192545127,"remaining_time":0.2168451225},
{"learn":[0.2928950744],"iteration":910,"passed_time":2.195096425,"remaining_time":0.2144495958},
{"learn":[0.2926566084],"iteration":911,"passed_time":2.198530389,"remaining_time":0.2121388972},
{"learn":[0.2924137881],"iteration":912,"passed_time":2.201882237,"remaining_time":0.209817913},
{"learn":[0.2921628814],"iteration":913,"passed_time":2.204003302,"remaining_time":0.2073788665},
{"learn":[0.2920799649],"iteration":914,"passed_time":2.206533603,"remaining_time":0.2049785315},
{"learn":[0.2918603806],"iteration":915,"passed_time":2.211097188,"remaining_time":0.202764371},
{"learn":[0.2917318875],"iteration":916,"passed_time":2.217292799,"remaining_time":0.2006928051},
{"learn":[0.2915854805],"iteration":917,"passed_time":2.222228711,"remaining_time":0.1984997323},
{"learn":[0.2915088748],"iteration":918,"passed_time":2.2355733,"remaining_time":0.1970418252},
{"learn":[0.2913700722],"iteration":919,"passed_time":2.238711798,"remaining_time":0.1946705911},
{"learn":[0.2911308501],"iteration":920,"passed_time":2.24230883,"remaining_time":0.1923370223},
{"learn":[0.2909214993],"iteration":921,"passed_time":2.247916001,"remaining_time":0.190170768},
{"learn":[0.2907890793],"iteration":922,"passed_time":2.26063859,"remaining_time":0.1885906516},
{"learn":[0.2906758245],"iteration":923,"passed_time":2.265096698,"remaining_time":0.1863066548},
{"learn":[0.2904378625],"iteration":924,"passed_time":2.267994376,"remaining_time":0.1838914359},
{"learn":[0.2903794442],"iteration":925,"passed_time":2.270102988,"remaining_time":0.1814121178},
{"learn":[0.2902885225],"iteration":926,"passed_time":2.274630417,"remaining_time":0.1791240781},
{"learn":[0.2901785258],"iteration":927,"passed_time":2.278693752,"remaining_time":0.1767952049},
{"learn":[0.2901651979],"iteration":928,"passed_time":2.281196506,"remaining_time":0.1743433282},
{"learn":[0.2900596908],"iteration":929,"passed_time":2.286340835,"remaining_time":0.1720901704},
{"learn":[0.2899408027],"iteration":930,"passed_time":2.290242252,"remaining_time":0.1697386846},
{"learn":[0.2897030272],"iteration":931,"passed_time":2.296617054,"remaining_time":0.1675643344},
{"learn":[0.2895135275],"iteration":932,"passed_time":2.300153278,"remaining_time":0.1651771379},
{"learn":[0.2894383557],"iteration":933,"passed_time":2.30292181,"remaining_time":0.1627332328},
{"learn":[0.2893759467],"iteration":934,"passed_time":2.314046377,"remaining_time":0.1608695343},
{"learn":[0.2892985839],"iteration":935,"passed_time":2.319002179,"remaining_time":0.1585642516},
{"learn":[0.2890885083],"iteration":936,"passed_time":2.324242875,"remaining_time":0.1562724665},
{"learn":[0.2887820309],"iteration":937,"passed_time":2.327298705,"remaining_time":0.1538299783},
{"learn":[0.2886284653],"iteration":938,"passed_time":2.331079198,"remaining_time":0.1514332599},
{"learn":[0.2883417004],"iteration":939,"passed_time":2.333290702,"remaining_time":0.1489334491},
{"learn":[0.288228706],"iteration":940,"passed_time":2.339943568,"remaining_time":0.146712721},
{"learn":[0.2880889359],"iteration":941,"passed_time":2.343646599,"remaining_time":0.1443009583},
{"learn":[0.2880221281],"iteration":942,"passed_time":2.346522507,"remaining_time":0.1418364612},
{"learn":[0.2879010041],"iteration":943,"passed_time":2.350896685,"remaining_time":0.1394599729},
{"learn":[0.2876034209],"iteration":944,"passed_time":2.354556674,"remaining_time":0.13703769},
{"learn":[0.2874290748],"iteration":945,"passed_time":2.358169766,"remaining_time":0.1346101135},
{"learn":[0.2872818611],"iteration":946,"passed_time":2.360743785,"remaining_time":0.1321218802},
{"learn":[0.2871098291],"iteration":947,"passed_time":2.367552932,"remaining_time":0.1298657727},
{"learn":[0.286954545],"iteration":948,"passed_time":2.370628289,"remaining_time":0.1273994128},
{"learn":[0.2868072868],"iteration":949,"passed_time":2.375846191,"remaining_time":0.1250445364},
{"learn":[0.2866106465],"iteration":950,"passed_time":2.378374673,"remaining_time":0.1225450673},
{"learn":[0.2865568007],"iteration":951,"passed_time":2.383450141,"remaining_time":0.1201739567},
{"learn":[0.2863527454],"iteration":952,"passed_time":2.385605705,"remaining_time":0.117653167},
{"learn":[0.2862045183],"iteration":953,"passed_time":2.388265554,"remaining_time":0.1151574586},
{"learn":[0.286125871],"iteration":954,"passed_time":2.390386766,"remaining_time":0.1126360256},
{"learn":[0.2860101447],"iteration":955,"passed_time":2.393199061,"remaining_time":0.1101472371},
{"learn":[0.2858774524],"iteration":956,"passed_time":2.396676726,"remaining_time":0.107687669},
{"learn":[0.2858285258],"iteration":957,"passed_time":2.399081161,"remaining_time":0.1051789235},
{"learn":[0.2854680483],"iteration":958,"passed_time":2.401939627,"remaining_time":0.1026898068},
{"learn":[0.2853140513],"iteration":959,"passed_time":2.403764096,"remaining_time":0.1001568373},
{"learn":[0.2850141409],"iteration":960,"passed_time":2.405589737,"remaining_time":0.09762538996},
{"learn":[0.2849221877],"iteration":961,"passed_time":2.408739788,"remaining_time":0.09514772552},
{"learn":[0.2848406552],"iteration":962,"passed_time":2.412451412,"remaining_time":0.09269024115},
{"learn":[0.2846801179],"iteration":963,"passed_time":2.41496816,"remaining_time":0.09018553293},
{"learn":[0.2844856385],"iteration":964,"passed_time":2.416659609,"remaining_time":0.08765086664},
{"learn":[0.2843758459],"iteration":965,"passed_time":2.418336294,"remaining_time":0.08511742648},
{"learn":[0.2842504473],"iteration":966,"passed_time":2.421937714,"remaining_time":0.08265144216},
{"learn":[0.2841289085],"iteration":967,"passed_time":2.427570012,"remaining_time":0.08025024835},
{"learn":[0.2840323071],"iteration":968,"passed_time":2.429689385,"remaining_time":0.07773000096},
{"learn":[0.2838756543],"iteration":969,"passed_time":2.432223439,"remaining_time":0.07522340533},
{"learn":[0.2836922167],"iteration":970,"passed_time":2.43485474,"remaining_time":0.07271965753},
{"learn":[0.2836057856],"iteration":971,"passed_time":2.459876726,"remaining_time":0.07086064644},
{"learn":[0.2835319843],"iteration":972,"passed_time":2.464312329,"remaining_time":0.06838276761},
{"learn":[0.2834077407],"iteration":973,"passed_time":2.467835148,"remaining_time":0.06587650292},
{"learn":[0.2833013388],"iteration":974,"passed_time":2.474923209,"remaining_time":0.06345956947},
{"learn":[0.28307334],"iteration":975,"passed_time":2.477780866,"remaining_time":0.06092903768},
{"learn":[0.2829635127],"iteration":976,"passed_time":2.482619968,"remaining_time":0.05844448237},
{"learn":[0.2826680728],"iteration":977,"passed_time":2.491070872,"remaining_time":0.05603635909},
{"learn":[0.2825278665],"iteration":978,"passed_time":2.493816096,"remaining_time":0.05349350156},
{"learn":[0.2823149078],"iteration":979,"passed_time":2.498462415,"remaining_time":0.05098902889},
{"learn":[0.2821406818],"iteration":980,"passed_time":2.503179144,"remaining_time":0.04848155325},
{"learn":[0.2820323017],"iteration":981,"passed_time":2.50645517,"remaining_time":0.04594317012},
{"learn":[0.2818335648],"iteration":982,"passed_time":2.509651426,"remaining_time":0.04340190665},
{"learn":[0.2817539409],"iteration":983,"passed_time":2.511749233,"remaining_time":0.04084145094},
{"learn":[0.2814944975],"iteration":984,"passed_time":2.514793304,"remaining_time":0.03829634474},
{"learn":[0.2813582872],"iteration":985,"passed_time":2.519796861,"remaining_time":0.03577804873},
{"learn":[0.281201677],"iteration":986,"passed_time":2.525482396,"remaining_time":0.03326369923},
{"learn":[0.2809891747],"iteration":987,"passed_time":2.52781949,"remaining_time":0.03070226101},
{"learn":[0.2808639269],"iteration":988,"passed_time":2.532893766,"remaining_time":0.02817172035},
{"learn":[0.2807887263],"iteration":989,"passed_time":2.535372224,"remaining_time":0.02560982045},
{"learn":[0.2807284274],"iteration":990,"passed_time":2.537916592,"remaining_time":0.02304868751},
{"learn":[0.2806111816],"iteration":991,"passed_time":2.541261339,"remaining_time":0.02049404306},
{"learn":[0.2805229487],"iteration":992,"passed_time":2.544144063,"remaining_time":0.01793455029},
{"learn":[0.2804922402],"iteration":993,"passed_time":2.547986224,"remaining_time":0.01538019854},
{"learn":[0.2802775198],"iteration":994,"passed_time":2.55177814,"remaining_time":0.01282300573},
{"learn":[0.2801011594],"iteration":995,"passed_time":2.553855771,"remaining_time":0.01025644888},
{"learn":[0.2798328696],"iteration":996,"passed_time":2.55661122,"remaining_time":0.007692912396},
{"learn":[0.2797659277],"iteration":997,"passed_time":2.560949904,"remaining_time":0.005132164137},
{"learn":[0.2797011018],"iteration":998,"passed_time":2.566138846,"remaining_time":0.002568707553},
{"learn":[0.2796076751],"iteration":999,"passed_time":2.568110797,"remaining_time":0}
]}